Workbook

Sheet ALGN(IS)
A2: Align Technology Inc (ALGN US) - Adjusted
A4: In Millions of USD except Per Share | C4: FY 2007 | D4: FY 2008 | E4: FY 2009 | F4: FY 2010 | G4: FY 2011 | H4: FY 2012 | I4: FY 2013 | J4: FY 2014 | K4: FY 2015 | T4: Last 12M | U4: FY 2016 Est | V4: FY 2017 Est
A5: 12 Months Ending | C5: 12/31/2007 | D5: 12/31/2008 | E5: 12/31/2009 | F5: 12/31/2010 | G5: 12/31/2011 | H5: 12/31/2012 | I5: 12/31/2013 | J5: 12/31/2014 | K5: 12/31/2015 | L5: 2016 | M5: 2017 | N5: 2018 | O5: 2019 | P5: 2020 | Q5: CAGR | R5: AVG | T5: 09/30/2016 | U5: 12/31/2016 | V5: 12/31/2017
A6: Revenue | B6: SALES_REV_TURN | C6: 284.332 | D6: 303.976 | E6: 312.333 | F6: 387.126 | G6: 479.741 | H6: 560.041 | I6: 660.206 | J6: 761.653 | K6: 845.486 | L6: =K6*(1+L7) -> 972.3089 | M6: =L6*(1+M7) -> 1118.1552 | N6: =M6*(1+N7) -> 1252.3339 | O6: =N6*(1+O7) -> 1377.5672 | P6: =O6*(1+P7) -> 1515.324 | T6: 1016.947 | U6: 1078.538 | V6: 1286.154
A7: %yoy | D7: =(D6-C6)/C6 -> 0.069088249 | E7: =(E6-D6)/D6 -> 0.027492302 | F7: =(F6-E6)/E6 -> 0.23946557 | G7: =(G6-F6)/F6 -> 0.23923735 | H7: =(H6-G6)/G6 -> 0.16738198 | I7: =(I6-H6)/H6 -> 0.17885298 | J7: =(J6-I6)/I6 -> 0.15365962 | K7: =(K6-J6)/J6 -> 0.11006718 | L7: 0.15 | M7: 0.15 | N7: 0.12 | O7: 0.1 | P7: 0.1 | Q7: =(K6/G6)^(1/5)-1 -> 0.12000489 | R7: =AVERAGE(G7:K7) -> 0.16983982
A8: + Sales & Services Revenue | B8: IS_SALES_AND_SERVICES_REVENUES | C8: — | D8: — | E8: 312.333 | F8: 387.126 | G8: 479.741 | H8: 560.041 | I8: 660.206 | J8: 761.653 | K8: 845.486 | T8: 1016.947
A9: - Cost of Revenue | B9: IS_COGS_TO_FE_AND_PP_AND_G | C9: 75.035 | D9: 78.85 | E9: 78.841 | F9: 83.709 | G9: 117.306 | H9: 142.918 | I9: 162.1 | J9: 183.21 | K9: 205.376 | L9: =L$6*L10 -> 233.35414 | M9: =M$6*M10 -> 268.35726 | N9: =N$6*N10 -> 300.56013 | O9: =O$6*O10 -> 330.61614 | P9: =P$6*P10 -> 363.67775 | T9: 249.092
A10: % reveneue | C10: =C9/C$6 -> 0.26389924 | D10: =D9/D$6 -> 0.25939548 | E10: =E9/E$6 -> 0.2524261 | F10: =F9/F$6 -> 0.21623192 | G10: =G9/G$6 -> 0.24451944 | H10: =H9/H$6 -> 0.25519203 | I10: =I9/I$6 -> 0.24552943 | J10: =J9/J$6 -> 0.24054261 | K10: =K9/K$6 -> 0.24290881 | L10: 0.24 | M10: 0.24 | N10: 0.24 | O10: 0.24 | P10: 0.24 | Q10: =(K9/G9)^(1/5)-1 -> 0.11852551 | R10: =AVERAGE(G10:K10) -> 0.24573846
A11: + Cost of Goods & Services | B11: IS_COG_AND_SERVICES_SOLD | C11: — | D11: — | E11: 78.841 | F11: 83.709 | G11: 117.306 | H11: 142.918 | I11: 162.1 | J11: 183.21 | K11: 205.376 | T11: 249.092
A12: Gross Profit | B12: GROSS_PROFIT | C12: 209.297 | D12: 225.126 | E12: 233.492 | F12: 303.417 | G12: 362.435 | H12: 417.123 | I12: 498.106 | J12: 578.443 | K12: 640.11 | L12: =L6-L9 -> 738.95476 | M12: =M6-M9 -> 849.79798 | N12: =N6-N9 -> 951.77374 | O12: =O6-O9 -> 1046.9511 | P12: =P6-P9 -> 1151.6462 | T12: 767.855 | U12: 814.56582 | V12: 972.49962
A13: + Other Operating Income | B13: IS_OTHER_OPER_INC | C13: — | D13: — | E13: 0 | F13: 0 | G13: 0 | H13: 0 | I13: 0 | J13: 0 | K13: 0 | T13: 0
A14: - Operating Expenses | B14: IS_OPERATING_EXPN | C14: 177.238 | D14: 203.381 | E14: 196.512 | F14: 204.8 | G14: 260.963 | H14: 292.889 | I14: 336.881 | J14: 384.867 | K14: 451.476 | L14: =SUM(L15,L19,L21,L23) -> 508.0314 | M14: =SUM(M15,M19,M21,M23) -> 584.23611 | N14: =SUM(N15,N19,N21,N23) -> 654.34444 | O14: =SUM(O15,O19,O21,O23) -> 719.77889 | P14: =SUM(P15,P19,P21,P23) -> 791.75678 | T14: 527.967
A15: + Selling, General & Admin | B15: IS_SG&A_EXPENSE | C15: 151.511 | D15: 177.216 | E15: 174.26 | F15: 178.803 | G15: 221.694 | H15: 247.881 | I15: 292.798 | J15: 332.068 | K15: 390.239 | L15: =L$6*L16 -> 437.539 | M15: =M$6*M16 -> 503.16986 | N15: =N$6*N16 -> 563.55024 | O15: =O$6*O16 -> 619.90526 | P15: =P$6*P16 -> 681.89579 | T15: 459.967
A16: % reveneue | C16: =C15/C$6 -> 0.53286651 | D16: =D15/D$6 -> 0.58299339 | E16: =E15/E$6 -> 0.55793016 | F16: =F15/F$6 -> 0.46187288 | G16: =G15/G$6 -> 0.46211185 | H16: =H15/H$6 -> 0.44261224 | I16: =I15/I$6 -> 0.44349491 | J16: =J15/J$6 -> 0.43598332 | K16: =K15/K$6 -> 0.46155584 | L16: 0.45 | M16: 0.45 | N16: 0.45 | O16: 0.45 | P16: 0.45 | Q16: =(K15/G15)^(1/5)-1 -> 0.11973524 | R16: =AVERAGE(G16:K16) -> 0.44915163
A17: + Selling & Marketing | B17: IS_SELLING_EXPENSES | C17: 98.231 | D17: 115.062 | E17: 112.542 | F17: 114.013 | G17: 142.174 | H17: 152.041 | I17: 180.046 | J17: 217.262 | K17: —
A18: + General & Administrative | B18: IS_GENERAL_AND_ADMINISTRATIVE | C18: — | D18: — | E18: 61.718 | F18: 64.79 | G18: 79.52 | H18: 95.84 | I18: 112.752 | J18: 114.806 | K18: —
A19: + Research & Development | B19: IS_OPEX_R&D | C19: — | D19: — | E19: 22.252 | F19: 25.997 | G19: 37.154 | H19: 42.869 | I19: 44.083 | J19: 52.799 | K19: 61.237 | L19: =L$6*L20 -> 70.492395 | M19: =M$6*M20 -> 81.066255 | N19: =N$6*N20 -> 90.794205 | O19: =O$6*O20 -> 99.873626 | P19: =P$6*P20 -> 109.86099 | T19: 68
A20: % reveneue | C20: =C19/C$6 -> #VALUE! | D20: =D19/D$6 -> #VALUE! | E20: =E19/E$6 -> 0.071244473 | F20: =F19/F$6 -> 0.067153847 | G20: =G19/G$6 -> 0.077445955 | H20: =H19/H$6 -> 0.076546181 | I20: =I19/I$6 -> 0.066771583 | J20: =J19/J$6 -> 0.069321594 | K20: =K19/K$6 -> 0.072428166 | L20: 0.0725 | M20: 0.0725 | N20: 0.0725 | O20: 0.0725 | P20: 0.0725 | Q20: =(K19/G19)^(1/5)-1 -> 0.10510022 | R20: =AVERAGE(G20:K20) -> 0.072502696
A21: + Depreciation & Amortization | B21: IS_DEPRECIATION_AND_AMORTIZATION | C21: — | D21: — | E21: — | F21: — | G21: 2.443 | H21: 3.455 | I21: — | J21: — | K21: — | L21: =L$6*L22 -> 0 | M21: =M$6*M22 -> 0 | N21: =N$6*N22 -> 0 | O21: =O$6*O22 -> 0 | P21: =P$6*P22 -> 0
A22: % reveneue | C22: =C21/C$6 -> #VALUE! | D22: =D21/D$6 -> #VALUE! | E22: =E21/E$6 -> #VALUE! | F22: =F21/F$6 -> #VALUE! | G22: =G21/G$6 -> 0.0050923311 | H22: =H21/H$6 -> 0.0061691912 | I22: =I21/I$6 -> #VALUE! | J22: =J21/J$6 -> #VALUE! | K22: =K21/K$6 -> #VALUE! | L22: 0 | M22: 0 | N22: 0 | O22: 0 | P22: 0 | Q22: =(K21/G21)^(1/5)-1 -> #VALUE! | R22: =AVERAGE(G22:K22) -> #VALUE!
A23: + Other Operating Expense | B23: IS_OTHER_OPERATING_EXPENSES | C23: — | D23: — | E23: 0 | F23: 0 | G23: -0.328 | H23: -1.316 | I23: 0 | J23: 0 | K23: 0 | L23: =L$6*L24 -> 0 | M23: =M$6*M24 -> 0 | N23: =N$6*N24 -> 0 | O23: =O$6*O24 -> 0 | P23: =P$6*P24 -> 0 | T23: 0
A24: % reveneue | C24: =C23/C$6 -> #VALUE! | D24: =D23/D$6 -> #VALUE! | E24: =E23/E$6 -> 0 | F24: =F23/F$6 -> 0 | G24: =G23/G$6 -> -0.00068370225 | H24: =H23/H$6 -> -0.002349828 | I24: =I23/I$6 -> 0 | J24: =J23/J$6 -> 0 | K24: =K23/K$6 -> 0 | L24: 0 | M24: 0 | N24: 0 | O24: 0 | P24: 0 | Q24: =(K23/G23)^(1/5)-1 -> -1 | R24: =AVERAGE(G24:K24) -> -0.00060670604
A25: Operating Income (Loss) | B25: IS_OPER_INC | C25: 32.059 | D25: 21.745 | E25: 36.98 | F25: 98.617 | G25: 101.472 | H25: 124.234 | I25: 161.225 | J25: 193.576 | K25: 188.634 | L25: =L12-L14 -> 230.92336 | M25: =M12-M14 -> 265.56187 | N25: =N12-N14 -> 297.42929 | O25: =O12-O14 -> 327.17222 | P25: =P12-P14 -> 359.88944 | T25: 239.888 | U25: 249.5 | V25: 312.583
A26: - Non-Operating (Income) Loss | B26: IS_NONOP_INCOME_LOSS | C26: — | D26: — | E26: -0.119 | F26: 0.731 | G26: 0.419 | H26: 1.296 | I26: 1.073 | J26: 3.207 | K26: 2.533 | T26: -1.474
A27: + Interest Expense, Net | B27: IS_NET_INTEREST_EXPENSE | C27: -3.853 | D27: -3.028 | E27: -0.494 | F27: -0.536 | G27: -0.501 | H27: — | I27: — | J27: — | K27: —
A28: + Interest Expense | B28: IS_INT_EXPENSE | C28: 0.342 | D28: 0.024 | E28: 0.085 | F28: 0.019 | G28: 0.051 | H28: — | I28: — | J28: — | K28: —
A29: - Interest Income | B29: IS_INT_INC | C29: 4.195 | D29: 3.052 | E29: 0.579 | F29: 0.555 | G29: 0.552 | H29: 0.757 | I29: — | J29: — | K29: —
A30: + Foreign Exch (Gain) Loss | B30: IS_FOREIGN_EXCH_LOSS | C30: 0 | D30: 0 | E30: 0 | F30: 0 | G30: 0 | H30: 0 | I30: 0 | J30: 0 | K30: 0
A31: + (Income) Loss from Affiliates | B31: INCOME_LOSS_FROM_AFFILIATES | C31: — | D31: — | E31: 0 | F31: 0 | G31: 0 | H31: 0 | I31: 0 | J31: 0 | K31: 0
A32: + Other Non-Op (Income) Loss | B32: IS_OTHER_NON_OPERATING_INC_LOSS | C32: — | D32: — | E32: 0.375 | F32: 1.267 | G32: 0.92 | H32: 2.053 | I32: 1.073 | J32: 3.207 | K32: 2.533 | T32: -1.474
A33: Pretax Income (Loss), Adjusted | B33: PRETAX_INC | C33: 36.95 | D33: 17.076 | E33: 37.099 | F33: 97.886 | G33: 101.053 | H33: 122.938 | I33: 160.152 | J33: 190.369 | K33: 186.101 | T33: 241.362 | U33: 251.889 | V33: 317.889
A34: - Abnormal Losses (Gains) | B34: IS_ABNORMAL_ITEM | C34: -1.796 | D34: -58.377 | E34: 70.992 | F34: -4.117 | G34: 11.112 | H34: 38.642 | I34: 67.013 | J34: 0 | K34: 0 | T34: 0
A35: + Merger/Acquisition Expense | B35: IS_MERGER_ACQUISITION_EXPENSE | C35: — | D35: — | E35: — | F35: — | G35: 10.03 | H35: 1.271 | I35: — | J35: — | K35: —
A36: + Asset Write-Down | B36: IS_IMPAIRMENT_ASSETS | C36: — | D36: — | E36: — | F36: — | G36: — | H36: — | I36: 26.32 | J36: — | K36: —
A37: + Impairment of Goodwill | B37: IS_IMPAIRMENT_GOODWILL_INTANGIBL | C37: — | D37: — | E37: — | F37: — | G37: — | H37: 36.591 | I37: 40.693 | J37: — | K37: —
A38: + Legal Settlement | B38: IS_LEGAL_LITIGATION_SETTLEMENT | C38: — | D38: — | E38: 69.673 | F38: 4.549 | G38: — | H38: — | I38: — | J38: — | K38: —
A39: + Restructuring | B39: IS_RESTRUCTURING_EXPENSES | C39: — | D39: — | E39: 1.319 | F39: — | G39: 1.082 | H39: 0.78 | I39: — | J39: — | K39: —
A40: + Insurance Settlement | B40: IS_INSURANCE_SETTLEMENTS | C40: — | D40: — | E40: — | F40: -8.666 | G40: — | H40: — | I40: — | J40: — | K40: —
A41: Pretax Income (Loss), GAAP | B41: PRETAX_INC | C41: 36.95 | D41: 17.076 | E41: -33.893 | F41: 102.003 | G41: 89.941 | H41: 84.296 | I41: 93.139 | J41: 190.369 | K41: 186.101 | T41: 241.362 | U41: 251.889 | V41: 317.889
A42: - Income Tax Expense (Benefit) | B42: IS_INC_TAX_EXP | C42: 1.226 | D42: -62.911 | E42: -2.624 | F42: 27.75 | G42: 23.225 | H42: 25.605 | I42: 28.844 | J42: 44.537 | K42: 42.081 | T42: 49.947
A43: + Current Income Tax | B43: IS_CURRENT_INCOME_TAX_BENEFIT | C43: — | D43: — | E43: -0.012 | F43: 1.583 | G43: 1.552 | H43: 1.611 | I43: 4.374 | J43: 5.327 | K43: 36.172
A44: + Deferred Income Tax | B44: IS_DEFERRED_INCOME_TAX_BENEFIT | C44: — | D44: — | E44: -2.612 | F44: 26.167 | G44: 21.673 | H44: 23.994 | I44: 24.47 | J44: 39.21 | K44: 5.909
A45: + Tax Allowance/Credit | B45: IS_TAX_VALN_ALLOWNCE_CREDITS | C45: — | D45: — | E45: 0 | F45: 0 | G45: 0 | H45: 0 | I45: 0 | J45: 0 | K45: —
A46: Income (Loss) from Cont Ops | B46: IS_INC_BEF_XO_ITEM | C46: 35.724 | D46: 79.987 | E46: -31.269 | F46: 74.253 | G46: 66.716 | H46: 58.691 | I46: 64.295 | J46: 145.832 | K46: 144.02 | T46: 190.938 | U46: 193.222 | V46: 238.222
A47: - Net Extraordinary Losses (Gains) | B47: XO_GL_NET_OF_TAX | C47: 0 | D47: 0 | E47: 0 | F47: 0 | G47: 0 | H47: 0 | I47: 0 | J47: 0 | K47: 0 | T47: 0
A48: + Discontinued Operations | B48: IS_DISCONTINUED_OPERATIONS | C48: — | D48: — | E48: 0 | F48: 0 | G48: 0 | H48: 0 | I48: 0 | J48: 0 | K48: 0 | T48: 0
A49: + XO & Accounting Changes | B49: IS_EXTRAORD_ITEMS_&_ACCTG_CHNG | C49: — | D49: — | E49: 0 | F49: 0 | G49: 0 | H49: 0 | I49: 0 | J49: 0 | K49: 0 | T49: 0
A50: Income (Loss) Incl. MI | B50: NI_INCLUDING_MINORITY_INT_RATIO | C50: 35.724 | D50: 79.987 | E50: -31.269 | F50: 74.253 | G50: 66.716 | H50: 58.691 | I50: 64.295 | J50: 145.832 | K50: 144.02 | T50: 190.938
A51: - Minority Interest | B51: MIN_NONCONTROL_INTEREST_CREDITS | C51: 0 | D51: 0 | E51: 0 | F51: 0 | G51: 0 | H51: 0 | I51: 0 | J51: 0 | K51: 0 | T51: 0
A52: Net Income, GAAP | B52: NET_INCOME | C52: 35.724 | D52: 79.987 | E52: -31.269 | F52: 74.253 | G52: 66.716 | H52: 58.691 | I52: 64.295 | J52: 145.832 | K52: 144.02 | T52: 190.938 | U52: 193.222 | V52: 238.222
A53: - Preferred Dividends | B53: IS_TOT_CASH_PFD_DVD | C53: 0 | D53: 0 | E53: 0 | F53: 0 | G53: 0 | H53: 0 | I53: 0 | J53: 0 | K53: 0 | T53: 0
A54: - Other Adjustments | B54: OTHER_ADJUSTMENTS | C54: 0 | D54: 0 | E54: 0 | F54: 0 | G54: 0 | H54: 0 | I54: 0 | J54: 0 | K54: 0 | T54: 0
A55: Net Income Avail to Common, GAAP | B55: EARN_FOR_COMMON | C55: 35.724 | D55: 79.987 | E55: -31.269 | F55: 74.253 | G55: 66.716 | H55: 58.691 | I55: 64.295 | J55: 145.832 | K55: 144.02 | T55: 190.938 | U55: 193.222 | V55: 238.222
A57: Net Income Avail to Common, Adj | B57: EARN_FOR_COMMON | C57: 35.724 | D57: 79.987 | E57: 14.85545 | F57: 71.57695 | G57: 73.9388 | H57: 83.8083 | I57: 107.85345 | J57: 145.832 | K57: 144.02 | T57: 190.938 | U57: 196.7 | V57: 242.6
A58: Net Abnormal Losses (Gains) | B58: IS_NET_ABNORMAL_ITEMS | C58: — | D58: — | E58: 46.12445 | F58: -2.67605 | G58: 7.2228 | H58: 25.1173 | I58: 43.55845 | J58: 0 | K58: 0 | T58: 0
A59: Net Extraordinary Losses (Gains) | B59: XO_GL_NET_OF_TAX | C59: 0 | D59: 0 | E59: 0 | F59: 0 | G59: 0 | H59: 0 | I59: 0 | J59: 0 | K59: 0 | T59: 0
A61: Basic Weighted Avg Shares | B61: IS_AVG_NUM_SH_FOR_EPS | C61: 67.176 | D61: 66.812 | E61: 69.094 | F61: 75.825 | G61: 77.988 | H61: 80.529 | I61: 80.551 | J61: 80.754 | K61: 79.998 | T61: 79.977
A62: Basic EPS, GAAP | B62: IS_EPS | C62: 0.53 | D62: 1.2 | E62: -0.45 | F62: 0.98 | G62: 0.86 | H62: 0.73 | I62: 0.8 | J62: 1.81 | K62: 1.8 | T62: 2.39 | U62: 2.41 | V62: 2.927
A63: Basic EPS from Cont Ops | B63: IS_EARN_BEF_XO_ITEMS_PER_SH | C63: 0.53 | D63: 1.2 | E63: -0.45 | F63: 0.98 | G63: 0.86 | H63: 0.73 | I63: 0.8 | J63: 1.81 | K63: 1.8 | T63: 2.39 | U63: 2.41 | V63: 2.927
A64: Basic EPS from Cont Ops, Adjusted | B64: IS_BASIC_EPS_CONT_OPS | C64: 0.51 | D64: 0.33 | E64: 0.215003 | F64: 0.943976 | G64: 0.948079 | H64: 1.040722 | I64: 1.338946 | J64: 1.81 | K64: 1.8 | T64: 2.39 | U64: 2.413 | V64: 2.992
A66: Diluted Weighted Avg Shares | B66: IS_SH_FOR_DILUTED_EPS | C66: 71.444 | D66: 68.064 | E66: 69.094 | F66: 78.08 | G66: 80.294 | H66: 83.04 | I66: 82.589 | J66: 82.283 | K66: 81.521 | T66: 81.466
A67: Diluted EPS, GAAP | B67: IS_DILUTED_EPS | C67: 0.5 | D67: 1.18 | E67: -0.45 | F67: 0.95 | G67: 0.83 | H67: 0.71 | I67: 0.78 | J67: 1.77 | K67: 1.77 | T67: 2.35 | U67: 2.41 | V67: 2.927
A68: Diluted EPS from Cont Ops | B68: IS_DIL_EPS_BEF_XO | C68: 0.5 | D68: 1.18 | E68: -0.45 | F68: 0.95 | G68: 0.83 | H68: 0.71 | I68: 0.78 | J68: 1.77 | K68: 1.77 | T68: 2.35 | U68: 2.41 | V68: 2.927
A69: Diluted EPS from Cont Ops, Adjusted | B69: IS_DIL_EPS_CONT_OPS | C69: 0.48 | D69: 0.32 | E69: 0.215003 | F69: 0.915727 | G69: 0.919954 | H69: 1.012472 | I69: 1.307412 | J69: 1.77 | K69: 1.77 | T69: 2.35 | U69: 2.413 | V69: 2.992
A71: Reference Items
A72: Accounting Standard | B72: ACCOUNTING_STANDARD | C72: US GAAP | D72: US GAAP | E72: US GAAP | F72: US GAAP | G72: US GAAP | H72: US GAAP | I72: US GAAP | J72: US GAAP | K72: US GAAP
A73: EBITDA | B73: EBITDA | C73: 45.444 | D73: 34.536 | E73: 49.984 | F73: 112.803 | G73: 118.949 | H73: 142.045 | I73: 178.05 | J73: 211.432 | K73: 206.638 | T73: 261.537 | U73: 272.125 | V73: 341.25
A74: EBITDA Margin (T12M) | B74: EBITDA_MARGIN | C74: 15.982724 | D74: 11.361423 | E74: 16.003432 | F74: 29.138575 | G74: 24.79442 | H74: 25.363322 | I74: 26.968855 | J74: 27.759623 | K74: 24.440144 | T74: 25.717859 | U74: 25.230914 | V74: 26.532593
A75: EBITA | B75: EBITA | C75: 35.244 | D75: 24.536 | E75: — | F75: 101.403 | G75: — | H75: — | I75: — | J75: 196.632 | K75: —
A76: EBIT | B76: EBIT | C76: 32.059 | D76: 21.745 | E76: 36.98 | F76: 98.617 | G76: 101.472 | H76: 124.234 | I76: 161.225 | J76: 193.576 | K76: 188.634 | T76: 239.888 | U76: 249.5 | V76: 312.583
A77: Gross Margin | B77: GROSS_MARGIN | C77: 73.610076 | D77: 74.060452 | E77: 74.75739 | F77: 78.376808 | G77: 75.548056 | H77: 74.480797 | I77: 75.447057 | J77: 75.945739 | K77: 75.709119 | T77: 75.505901 | U77: 75.525 | V77: 75.613
A78: Operating Margin | B78: OPER_MARGIN | C78: 11.275199 | D78: 7.153525 | E78: 11.839927 | F78: 25.474135 | G78: 21.151413 | H78: 22.183019 | I78: 24.420408 | J78: 25.415248 | K78: 22.310718 | T78: 23.589037 | U78: 23.133167 | V78: 24.303699
A79: Profit Margin | B79: PROF_MARGIN | C79: 12.564186 | D79: 26.313591 | E79: 4.756286 | F79: 18.489316 | G79: 15.412233 | H79: 14.964672 | I79: 16.336333 | J79: 19.146777 | K79: 17.03399 | T79: 18.77561 | U79: 18.237651 | V79: 18.862438
A80: Sales per Employee | B80: ACTUAL_SALES_PER_EMPL | C80: — | D80: — | E80: — | F80: — | G80: — | H80: — | I80: 193042.69 | J80: 212752.23 | K80: 193253.94
A81: Dividends per Share | B81: EQY_DPS | C81: 0 | D81: 0 | E81: 0 | F81: 0 | G81: 0 | H81: 0 | I81: 0 | J81: 0 | K81: 0 | T81: 0 | U81: 0 | V81: 0
A82: Total Cash Common Dividends | B82: IS_TOT_CASH_COM_DVD | C82: 0 | D82: 0 | E82: 0 | F82: 0 | G82: 0 | H82: 0 | I82: 0 | J82: 0 | K82: 0 | T82: 0
A83: Capitalized Interest Expense | B83: IS_CAP_INT_EXP | C83: — | D83: — | E83: — | F83: — | G83: — | H83: — | I83: — | J83: 0 | K83: 0 | T83: 0
A84: Export Sales | B84: IS_EXPORT_SALES | C84: 0 | D84: 0 | E84: — | F84: 0 | G84: — | H84: 0 | I84: — | J84: — | K84: —
A85: Depreciation Expense | B85: IS_DEPR_EXP | C85: 10.2 | D85: 10 | E85: — | F85: 11.4 | G85: — | H85: — | I85: — | J85: 14.8 | K85: —
A86: Rental Expense | B86: BS_CURR_RENTAL_EXPENSE | C86: 3.4 | D86: 3.8 | E86: 3.8 | F86: 4.7 | G86: 6.1 | H86: 6.9 | I86: 7.3 | J86: 7.6 | K86: 8.2
A87: Source: Bloomberg

Sheet ALGN(BS_Annual)
A2: Align Technology Inc (ALGN US) - Standardized
A4: In Millions of USD except Per Share | C4: FY 2007 | D4: FY 2008 | E4: FY 2009 | F4: FY 2010 | G4: FY 2011 | H4: FY 2012 | I4: FY 2013 | J4: FY 2014 | K4: FY 2015
A5: 12 Months Ending | C5: 12/31/2007 | D5: 12/31/2008 | E5: 12/31/2009 | F5: 12/31/2010 | G5: 12/31/2011 | H5: 12/31/2012 | I5: 12/31/2013 | J5: 12/31/2014 | K5: 12/31/2015
A6: Total Assets
A7: + Cash, Cash Equivalents & STI | B7: C&CE_AND_STI_DETAILED | C7: 127.89 | D7: 110.166 | E7: 186.465 | F7: 303.279 | G7: 248.07 | H7: 334.871 | I7: 369.993 | J7: 454.658 | K7: 527.295
A8: + Cash & Cash Equivalents | B8: BS_CASH_NEAR_CASH_ITEM | C8: 89.119 | D8: 87.1 | E8: 166.487 | F8: 294.664 | G8: 240.675 | H8: 306.386 | I8: 242.953 | J8: 199.871 | K8: 167.714
A9: + ST Investments | B9: BS_MKT_SEC_OTHER_ST_INVEST | C9: 38.771 | D9: 23.066 | E9: 19.978 | F9: 8.615 | G9: 7.395 | H9: 28.485 | I9: 127.04 | J9: 254.787 | K9: 359.581
A10: + Accounts & Notes Receiv | B10: BS_ACCT_NOTE_RCV | C10: 44.85 | D10: 52.362 | E10: 54.537 | F10: 65.43 | G10: 91.537 | H10: 98.992 | I10: 113.25 | J10: 129.751 | K10: 158.55
A11: + Accounts Receivable, Net | B11: BS_ACCTS_REC_EXCL_NOTES_REC | C11: 44.85 | D11: 52.362 | E11: 54.537 | F11: 65.43 | G11: 91.537 | H11: 98.992 | I11: 113.25 | J11: 129.751 | K11: 158.55
A12: + Notes Receivable, Net | B12: NOTES_RECEIVABLE | C12: — | D12: — | E12: 0 | F12: 0 | G12: 0 | H12: 0 | I12: 0 | J12: 0 | K12: 0
A13: + Inventories | B13: BS_INVENTORIES | C13: 2.91 | D13: 1.965 | E13: 2.046 | F13: 2.544 | G13: 9.402 | H13: 15.122 | I13: 13.968 | J13: 15.928 | K13: 19.465
A14: + Raw Materials | B14: INVTRY_RAW_MATERIALS | C14: 1.983 | D14: 1.066 | E14: 1.079 | F14: 1.272 | G14: 4.542 | H14: 7.629 | I14: 5.172 | J14: 8.143 | K14: 9.95
A15: + Work In Process | B15: INVTRY_IN_PROGRESS | C15: 0.631 | D15: 0.416 | E15: 0.46 | F15: 1.03 | G15: 2.486 | H15: 3.889 | I15: 4.241 | J15: 2.97 | K15: 7.067
A16: + Finished Goods | B16: INVTRY_FINISHED_GOODS | C16: 0.296 | D16: 0.483 | E16: 0.507 | F16: 0.242 | G16: 2.374 | H16: 3.604 | I16: 4.555 | J16: 4.815 | K16: 2.448
A17: + Other Inventory | B17: BS_OTHER_INV | C17: 0 | D17: 0 | E17: 0 | F17: 0 | G17: 0 | H17: 0 | I17: 0 | J17: 0 | K17: 0
A18: + Other ST Assets | B18: OTHER_CURRENT_ASSETS_DETAILED | C18: 8.867 | D18: 13.414 | E18: 18.251 | F18: 17.358 | G18: 35.807 | H18: 36.808 | I18: 47.465 | J18: 56.823 | K18: 26.7
A19: + Derivative & Hedging Assets | B19: BS_DERIV_&_HEDGING_ASSETS_ST | C19: — | D19: — | E19: 0 | F19: 0 | G19: 0 | H19: 0 | I19: 0 | J19: 0 | K19: 0
A20: + Deferred Tax Assets | B20: BS_DEFERRED_TAX_ASSETS_ST | C20: — | D20: — | E20: — | F20: — | G20: — | H20: — | I20: — | J20: 37.053 | K20: 0
A21: + Misc ST Assets | B21: BS_OTHER_CUR_ASSET_LESS_PREPAY | C21: — | D21: — | E21: 18.251 | F21: 17.358 | G21: 35.807 | H21: 36.808 | I21: 47.465 | J21: 19.77 | K21: 26.7
A22: Total Current Assets | B22: BS_CUR_ASSET_REPORT | C22: 184.517 | D22: 177.907 | E22: 261.299 | F22: 388.611 | G22: 384.816 | H22: 485.793 | I22: 544.676 | J22: 657.16 | K22: 732.01
A23: + Property, Plant & Equip, Net | B23: BS_NET_FIX_ASSET | C23: 25.32 | D23: 26.979 | E23: 24.971 | F23: 30.684 | G23: 53.965 | H23: 79.191 | I23: 75.743 | J23: 90.125 | K23: 136.473
A24: + Property, Plant & Equip | B24: BS_GROSS_FIX_ASSET | C24: 79.079 | D24: 88.342 | E24: 94.977 | F24: 98.458 | G24: 129.432 | H24: 165.126 | I24: 181.249 | J24: 197.927 | K24: 254.51
A25: - Accumulated Depreciation | B25: BS_ACCUM_DEPR | C25: 53.759 | D25: 61.363 | E25: 70.006 | F25: 67.774 | G25: 75.467 | H25: 85.935 | I25: 105.506 | J25: 107.802 | K25: 118.037
A26: + LT Investments & Receivables | B26: BS_LT_INVEST | C26: 0 | D26: 0 | E26: 0 | F26: 9.089 | G26: 0 | H26: 21.252 | I26: 101.978 | J26: 147.892 | K26: 151.37
A27: + LT Marketable Securities | B27: BS_LT_MARKETABLE_SECURITIES | C27: — | D27: — | E27: — | F27: 9.089 | G27: — | H27: 21.252 | I27: 101.978 | J27: 147.892 | K27: 151.37
A28: + Other LT Assets | B28: BS_OTHER_ASSETS_DEF_CHRG_OTHER | C28: 12.924 | D28: 74.455 | E28: 68.97 | F28: 48.559 | G28: 210.483 | H28: 170.076 | I28: 109.75 | J28: 92.82 | K28: 138.78
A29: + Total Intangible Assets | B29: BS_DISCLOSED_INTANGIBLES | C29: 11.093 | D29: 8.266 | E29: 5.466 | F29: 2.666 | G29: 185.405 | H29: 145.013 | I29: 85.362 | J29: 82.056 | K29: 79.162
A30: + Goodwill | B30: BS_GOODWILL | C30: 0.478 | D30: 0.478 | E30: 0.478 | F30: 0.478 | G30: 135.383 | H30: 99.236 | I30: 61.623 | J30: 61.369 | K30: 61.074
A31: + Other Intangible Assets | B31: OTHER_INTANGIBLE_ASSETS_DETAILED | C31: 10.615 | D31: 7.788 | E31: 4.988 | F31: 2.188 | G31: 50.022 | H31: 45.777 | I31: 23.739 | J31: 20.687 | K31: 18.088
A32: + Deferred Tax Assets | B32: BS_DEFERRED_TAX_ASSETS_LT | C32: — | D32: — | E32: 61.535 | F32: 42.439 | G32: 22.337 | H32: 21.609 | I32: 15.766 | J32: 3.099 | K32: 51.416
A33: + Derivative & Hedging Assets | B33: BS_DERIV_&_HEDGING_ASSETS_LT | C33: — | D33: — | E33: 0 | F33: 0 | G33: 0 | H33: 0 | I33: 0 | J33: 0 | K33: 0
A34: + Misc LT Assets | B34: OTHER_NONCURRENT_ASSETS_DETAILED | C34: 1.831 | D34: 66.189 | E34: 1.969 | F34: 3.454 | G34: 2.741 | H34: 3.454 | I34: 8.622 | J34: 7.665 | K34: 8.202
A35: Total Noncurrent Assets | B35: BS_TOT_NON_CUR_ASSET | C35: 38.244 | D35: 101.434 | E35: 93.941 | F35: 88.332 | G35: 264.448 | H35: 270.519 | I35: 287.471 | J35: 330.837 | K35: 426.623
A36: Total Assets | B36: BS_TOT_ASSET | C36: 222.761 | D36: 279.341 | E36: 355.24 | F36: 476.943 | G36: 649.264 | H36: 756.312 | I36: 832.147 | J36: 987.997 | K36: 1158.633
A38: Liabilities & Shareholders' Equity
A39: + Payables & Accruals | B39: ACCT_PAYABLE_&_ACCRUALS_DETAILED | C39: 9.222 | D39: 5.58 | E39: 48.944 | F39: 59.126 | G39: 95.865 | H39: 93.796 | I39: 98.063 | J39: 111.127 | K39: 142.119
A40: + Accounts Payable | B40: BS_ACCT_PAYABLE | C40: 9.222 | D40: 5.58 | E40: 6.122 | F40: 7.768 | G40: 19.265 | H40: 19.549 | I40: 17.718 | J40: 23.247 | K40: 34.354
A41: + Accrued Taxes | B41: BS_TAXES_PAYABLE | C41: — | D41: — | E41: 2.92 | F41: 1.936 | G41: 0.426 | H41: 0 | I41: 0 | J41: 0 | K41: 2.646
A42: + Interest & Dividends Payable | B42: BS_INTEREST_&_DIVIDENDS_PAYABLE | C42: — | D42: — | E42: 0 | F42: 0 | G42: 0 | H42: 0 | I42: 0 | J42: 0 | K42: 0
A43: + Other Payables & Accruals | B43: BS_ACCRUAL | C43: — | D43: — | E43: 39.902 | F43: 49.422 | G43: 76.174 | H43: 74.247 | I43: 80.345 | J43: 87.88 | K43: 105.119
A44: + ST Debt | B44: BS_ST_BORROW | C44: 0 | D44: 0 | E44: 0 | F44: 0 | G44: 0 | H44: 0 | I44: 0 | J44: 0 | K44: 0
A45: + ST Borrowings | B45: SHORT_TERM_DEBT_DETAILED | C45: 0 | D45: 0 | E45: 0 | F45: 0 | G45: 0 | H45: 0 | I45: 0 | J45: 0 | K45: 0
A46: + ST Capital Leases | B46: ST_CAPITAL_LEASE_OBLIGATIONS | C46: 0 | D46: 0 | E46: 0 | F46: 0 | G46: 0 | H46: 0 | I46: 0 | J46: 0 | K46: 0
A47: + Other ST Liabilities | B47: OTHER_CURRENT_LIABS_SUB_DETAILED | C47: 52.237 | D47: 54.992 | E47: 32.299 | F47: 33.848 | G47: 52.252 | H47: 61.975 | I47: 77.275 | J47: 90.684 | K47: 129.553
A48: + Deferred Revenue | B48: ST_DEFERRED_REVENUE | C48: — | D48: — | E48: 32.299 | F48: 33.848 | G48: 52.252 | H48: 61.975 | I48: 77.275 | J48: 90.684 | K48: 129.553
A49: + Derivatives & Hedging | B49: BS_DERIVATIVE_&_HEDGING_LIABS_ST | C49: — | D49: — | E49: 0 | F49: 0 | G49: 0 | H49: 0 | I49: 0 | J49: 0 | K49: 0
A50: + Misc ST Liabilities | B50: OTHER_CURRENT_LIABS_DETAILED | C50: 52.237 | D50: 54.992 | E50: 0 | F50: 0 | G50: 0 | H50: 0 | I50: 0 | J50: 0 | K50: 0
A51: Total Current Liabilities | B51: BS_CUR_LIAB | C51: 61.459 | D51: 60.572 | E51: 81.243 | F51: 92.974 | G51: 148.117 | H51: 155.771 | I51: 175.338 | J51: 201.811 | K51: 271.672
A52: + LT Debt | B52: BS_LT_BORROW | C52: 0 | D52: 0 | E52: 0 | F52: 0 | G52: 0 | H52: 0 | I52: 0 | J52: 0 | K52: 0
A53: + LT Borrowings | B53: LONG_TERM_BORROWINGS_DETAILED | C53: 0 | D53: 0 | E53: 0 | F53: 0 | G53: 0 | H53: 0 | I53: 0 | J53: 0 | K53: 0
A54: + LT Capital Leases | B54: LT_CAPITAL_LEASE_OBLIGATIONS | C54: 0 | D54: 0 | E54: 0 | F54: 0 | G54: 0 | H54: 0 | I54: 0 | J54: 0 | K54: 0
A55: + Other LT Liabilities | B55: OTHER_NONCUR_LIABS_SUB_DETAILED | C55: 0.148 | D55: 0.229 | E55: 0.961 | F55: 6.222 | G55: 10.366 | H55: 19.224 | I55: 22.839 | J55: 33.415 | K55: 39.035
A56: + Accrued Liabilities | B56: BS_ACCRUED_LIABILITIES | C56: — | D56: — | E56: 0 | F56: 0 | G56: 0 | H56: 0 | I56: 0 | J56: 0 | K56: 0
A57: + Pension Liabilities | B57: PENSION_LIABILITIES | C57: — | D57: — | E57: 0 | F57: 0 | G57: 0 | H57: 0 | I57: 0 | J57: 0 | K57: 0
A58: + Pensions | B58: BS_PENSIONS_LT_LIABS | C58: — | D58: — | E58: 0 | F58: 0 | G58: 0 | H58: 0 | I58: 0 | J58: 0 | K58: 0
A59: + Other Post-Ret Benefits | B59: BS_OPRB_LT_LIABS | C59: — | D59: — | E59: 0 | F59: 0 | G59: 0 | H59: 0 | I59: 0 | J59: 0 | K59: 0
A60: + Deferred Revenue | B60: LT_DEFERRED_REVENUE | C60: — | D60: — | E60: 0 | F60: 0 | G60: 0 | H60: 0 | I60: 0 | J60: 0 | K60: 0
A61: + Derivatives & Hedging | B61: BS_DERIVATIVE_&_HEDGING_LIABS_LT | C61: — | D61: — | E61: 0 | F61: 0 | G61: 0 | H61: 0 | I61: 0 | J61: 0 | K61: 0
A62: + Misc LT Liabilities | B62: OTHER_NONCURRENT_LIABS_DETAILED | C62: 0.148 | D62: 0.229 | E62: 0.961 | F62: 6.222 | G62: 10.366 | H62: 19.224 | I62: 22.839 | J62: 33.415 | K62: 39.035
A63: Total Noncurrent Liabilities | B63: NON_CUR_LIAB | C63: 0.148 | D63: 0.229 | E63: 0.961 | F63: 6.222 | G63: 10.366 | H63: 19.224 | I63: 22.839 | J63: 33.415 | K63: 39.035
A64: Total Liabilities | B64: BS_TOT_LIAB2 | C64: 61.607 | D64: 60.801 | E64: 82.204 | F64: 99.196 | G64: 158.483 | H64: 174.995 | I64: 198.177 | J64: 235.226 | K64: 310.707
A65: + Preferred Equity | B65: BS_PFD_EQY | C65: 0 | D65: 0 | E65: 0 | F65: 0 | G65: 0 | H65: 0 | I65: 0 | J65: 0 | K65: 0
A66: + Share Capital & APIC | B66: BS_SH_CAP_AND_APIC | C66: 450.147 | D66: 439.501 | E66: 525.08 | F66: 555.859 | G66: 607.248 | H66: 670.74 | I66: 729.586 | J66: 783.418 | K66: 821.515
A67: + Common Stock | B67: BS_COMMON_STOCK | C67: — | D67: — | E67: 0.007 | F67: 0.008 | G67: 0.008 | H67: 0.008 | I67: 0.008 | J67: 0.008 | K67: 0.008
A68: + Additional Paid in Capital | B68: BS_ADD_PAID_IN_CAP | C68: — | D68: — | E68: 525.073 | F68: 555.851 | G68: 607.24 | H68: 670.732 | I68: 729.578 | J68: 783.41 | K68: 821.507
A69: - Treasury Stock | B69: BS_AMT_OF_TSY_STOCK | C69: — | D69: 0 | E69: 0 | F69: 0 | G69: 0 | H69: 0 | I69: 0 | J69: 0 | K69: 0
A70: + Retained Earnings | B70: BS_PURE_RETAINED_EARNINGS | C70: -289.65 | D70: -221.23 | E70: -252.499 | F70: -178.246 | G70: -116.513 | H70: -89.626 | I70: -95.91 | J70: -30.507 | K70: 27.391
A71: + Other Equity | B71: OTHER_INS_RES_TO_SHRHLDR_EQY | C71: 0.657 | D71: 0.269 | E71: 0.455 | F71: 0.134 | G71: 0.046 | H71: 0.203 | I71: 0.294 | J71: -0.14 | K71: -0.98
A72: Equity Before Minority Interest | B72: EQTY_BEF_MINORITY_INT_DETAILED | C72: 161.154 | D72: 218.54 | E72: 273.036 | F72: 377.747 | G72: 490.781 | H72: 581.317 | I72: 633.97 | J72: 752.771 | K72: 847.926
A73: + Minority/Non Controlling Interest | B73: MINORITY_NONCONTROLLING_INTEREST | C73: 0 | D73: 0 | E73: 0 | F73: 0 | G73: 0 | H73: 0 | I73: 0 | J73: 0 | K73: 0
A74: Total Equity | B74: TOTAL_EQUITY | C74: 161.154 | D74: 218.54 | E74: 273.036 | F74: 377.747 | G74: 490.781 | H74: 581.317 | I74: 633.97 | J74: 752.771 | K74: 847.926
A75: Total Liabilities & Equity | B75: TOT_LIAB_AND_EQY | C75: 222.761 | D75: 279.341 | E75: 355.24 | F75: 476.943 | G75: 649.264 | H75: 756.312 | I75: 832.147 | J75: 987.997 | K75: 1158.633
A77: Reference Items
A78: Accounting Standard | B78: ACCOUNTING_STANDARD | C78: US GAAP | D78: US GAAP | E78: US GAAP | F78: US GAAP | G78: US GAAP | H78: US GAAP | I78: US GAAP | J78: US GAAP | K78: US GAAP
A79: Shares Outstanding | B79: BS_SH_OUT | C79: 68.642 | D79: 65.633 | E79: 74.568 | F79: 76.39 | G79: 78.776 | H79: 80.611 | I79: 80.583 | J79: 80.205 | K79: 79.5
A80: Number of Treasury Shares | B80: BS_NUM_OF_TSY_SH | C80: 0.04 | D80: 0 | E80: 0 | F80: 0 | G80: 0 | H80: 0 | I80: 0 | J80: 0 | K80: 0
A81: Future Minimum Operating Lease Obligations | B81: BS_FUTURE_MIN_OPER_LEASE_OBLIG | C81: 6.002 | D81: 9.687 | E81: 8.574 | F81: 22.836 | G81: 27.9 | H81: 25.718 | I81: 28.273 | J81: 24.046 | K81: 19.75
A82: Capital Leases - Total | B82: BS_TOTAL_CAPITAL_LEASES | C82: 0 | D82: 0 | E82: 0 | F82: 0 | G82: 0 | H82: 0 | I82: 0 | J82: 0 | K82: 0
A83: Options Granted During Period | B83: BS_OPTIONS_GRANTED | C83: 1.517 | D83: 2.182 | E83: 1.134 | F83: 1.501 | G83: 0.421 | H83: 0 | I83: 0 | J83: 0 | K83: 0
A84: Options Outstanding at Period End | B84: BS_OPTIONS_OUTSTANDING | C84: 7.133 | D84: 7.309 | E84: 7.488 | F84: 7.815 | G84: 6.19 | H84: 3.276 | I84: 1.321 | J84: 0.668 | K84: 0.496
A85: Net Debt | B85: NET_DEBT | C85: -127.89 | D85: -110.166 | E85: -186.465 | F85: -312.368 | G85: -248.07 | H85: -356.123 | I85: -471.971 | J85: -602.55 | K85: -678.665
A86: Net Debt to Equity | B86: NET_DEBT_TO_SHRHLDR_EQTY | C86: -79.358874 | D86: -50.409994 | E86: -68.293192 | F86: -82.692384 | G86: -50.545967 | H86: -61.261412 | I86: -74.446898 | J86: -80.044263 | K86: -80.038234
A87: Tangible Common Equity Ratio | B87: TCE_RATIO | C87: 70.894514 | D87: 77.570414 | E87: 76.497967 | F87: 79.084796 | G87: 65.833799 | H87: 71.373256 | I87: 73.462643 | J87: 74.035174 | K87: 71.216735
A88: Current Ratio | B88: CUR_RATIO | C88: 3.002278 | D88: 2.937116 | E88: 3.216265 | F88: 4.179781 | G88: 2.598054 | H88: 3.118636 | I88: 3.106434 | J88: 3.256314 | K88: 2.694462
A89: Cash Conversion Cycle | B89: CASH_CONVERSION_CYCLE | C89: 30.212406 | D89: 35.067773 | E89: 44.687182 | F89: 36.458665 | G89: 38.748096 | H89: 45.94695 | I89: 49.16292 | J89: 47.631398 | K89: 43.362648
A90: Number of Employees | B90: NUM_OF_EMPLOYEES | C90: — | D90: — | E90: — | F90: — | G90: — | H90: — | I90: 3420 | J90: 3580 | K90: 4375
A91: Source: Bloomberg

Sheet ALGN(CF)
A2: Align Technology Inc (ALGN US) - Standardized
A4: In Millions of USD except Per Share | C4: FY 2007 | D4: FY 2008 | E4: FY 2009 | F4: FY 2010 | G4: FY 2011 | H4: FY 2012 | I4: FY 2013 | J4: FY 2014 | K4: FY 2015 | S4: Last 12M
A5: 12 Months Ending | C5: 12/31/2007 | D5: 12/31/2008 | E5: 12/31/2009 | F5: 12/31/2010 | G5: 12/31/2011 | H5: 12/31/2012 | I5: 12/31/2013 | J5: 12/31/2014 | K5: 12/31/2015 | L5: 2016 | M5: 2017 | N5: 2018 | O5: 2019 | P5: 2020 | Q5: CAGR | R5: AVG | S5: 09/30/2016
A6: Cash from Operating Activities
A7: + Net Income | B7: CF_NET_INC | C7: 35.724 | D7: 79.987 | E7: -31.269 | F7: 74.253 | G7: 66.716 | H7: 58.691 | I7: 64.295 | J7: 145.832 | K7: 144.02 | S7: 190.938
A8: + Depreciation & Amortization | B8: CF_DEPR_AMORT | C8: 13.385 | D8: 12.791 | E8: 13.004 | F8: 14.186 | G8: 17.477 | H8: 17.811 | I8: 16.825 | J8: 17.856 | K8: 18.004 | L8: =L9*'ALGN(IS)'!L$6 -> 19.446178 | M8: =M9*'ALGN(IS)'!M$6 -> 22.363105 | N8: =N9*'ALGN(IS)'!N$6 -> 25.046677 | O8: =O9*'ALGN(IS)'!O$6 -> 27.551345 | P8: =P9*'ALGN(IS)'!P$6 -> 30.306479 | S8: 21.649
A9: % revenu | C9: =C8/'ALGN(IS)'!C$6 -> 0.04707525 | D9: =D8/'ALGN(IS)'!D$6 -> 0.04207898 | E9: =E8/'ALGN(IS)'!E$6 -> 0.04163505 | F9: =F8/'ALGN(IS)'!F$6 -> 0.0366444 | G9: =G8/'ALGN(IS)'!G$6 -> 0.036430074 | H9: =H8/'ALGN(IS)'!H$6 -> 0.031803029 | I9: =I8/'ALGN(IS)'!I$6 -> 0.02548447 | J9: =J8/'ALGN(IS)'!J$6 -> 0.023443747 | K9: =K8/'ALGN(IS)'!K$6 -> 0.021294262 | L9: 0.02 | M9: 0.02 | N9: 0.02 | O9: 0.02 | P9: 0.02 | Q9: =(K8/G8)^(1/5)-1 -> 0.0059593315 | R9: =AVERAGE(G9:K9) -> 0.027691116
A10: + Non-Cash Items | B10: NON_CASH_ITEMS_DETAILED | C10: 13.222 | D10: -44.721 | E10: 76.546 | F10: 30.497 | G10: 13.734 | H10: 60.659 | I10: 91.694 | J10: 54.017 | K10: 44.922 | S10: 32.755
A11: + Stock-Based Compensation | B11: CF_STOCK_BASED_COMPENSATION | C11: 12.211 | D11: 16.913 | E11: 15.725 | F11: 12.107 | G11: 7.774 | H11: 4.296 | I11: -0.665 | J11: 18.43 | K11: 42.547 | S11: 51.123
A12: + Deferred Income Taxes | B12: CF_DEF_INC_TAX | C12: 0 | D12: -64.608 | E12: -2.612 | F12: 17.307 | G12: 5.842 | H12: 17.783 | I12: 21.204 | J12: 25.481 | K12: -11.424 | S12: -32.917
A13: + Other Non-Cash Adj | B13: OTHER_NON_CASH_ADJ_LESS_DETAILED | C13: 1.011 | D13: 2.974 | E13: 63.433 | F13: 1.083 | G13: 0.118 | H13: 38.58 | I13: 71.155 | J13: 10.106 | K13: 13.799 | S13: 14.549
A14: + Chg in Non-Cash Work Cap | B14: CF_CHNG_NON_CASH_WORK_CAP | C14: -9.554 | D14: -8.311 | E14: 15.884 | F14: 10.593 | G14: 32.542 | H14: -3.383 | I14: 13.162 | J14: 9.194 | K14: 31.051 | L14: =L15*'ALGN(IS)'!L$6 -> 19.446178 | M14: =M15*'ALGN(IS)'!M$6 -> 22.363105 | N14: =N15*'ALGN(IS)'!N$6 -> 25.046677 | O14: =O15*'ALGN(IS)'!O$6 -> 27.551345 | P14: =P15*'ALGN(IS)'!P$6 -> 30.306479 | S14: 0.687
A15: % revenu | C15: =C14/'ALGN(IS)'!C$6 -> -0.033601564 | D15: =D14/'ALGN(IS)'!D$6 -> -0.027340974 | E15: =E14/'ALGN(IS)'!E$6 -> 0.050855977 | F15: =F14/'ALGN(IS)'!F$6 -> 0.027363184 | G15: =G14/'ALGN(IS)'!G$6 -> 0.067832435 | H15: =H14/'ALGN(IS)'!H$6 -> -0.0060406292 | I15: =I14/'ALGN(IS)'!I$6 -> 0.019936202 | J15: =J14/'ALGN(IS)'!J$6 -> 0.012071114 | K15: =K14/'ALGN(IS)'!K$6 -> 0.036725623 | L15: 0.02 | M15: 0.02 | N15: 0.02 | O15: 0.02 | P15: 0.02 | Q15: =(K14/G14)^(1/5)-1 -> -0.0093362537 | R15: =AVERAGE(G15:K15) -> 0.026104949
A16: + (Inc) Dec in Accts Receiv | B16: CF_ACCT_RCV_UNBILLED_REV | C16: -10.703 | D16: -7.951 | E16: -2.586 | F16: -12.184 | G16: -21.693 | H16: -9.138 | I16: -11.981 | J16: -27.229 | K16: -40.775 | S16: -106.774
A17: + (Inc) Dec in Inventories | B17: CF_CHANGE_IN_INVENTORIES | C17: 0.186 | D17: 0.943 | E17: -0.085 | F17: -0.508 | G17: -4.058 | H17: -5.718 | I17: 1.158 | J17: -1.999 | K17: -3.563 | S17: -7.4029999
A18: + Inc (Dec) in Accts Payable | B18: CF_CHANGE_IN_ACCOUNTS_PAYABLE | C18: 2.738 | D18: -2.651 | E18: -0.614 | F18: 2.612 | G18: 7.535 | H18: -0.006 | I18: -0.186 | J18: 2.887 | K18: 7.575 | S18: -0.967
A19: + Inc (Dec) in Other | B19: INC_DEC_IN_OT_OP_AST_LIAB_DETAIL | C19: -1.775 | D19: 1.348 | E19: 19.169 | F19: 20.673 | G19: 50.758 | H19: 11.479 | I19: 24.171 | J19: 35.535 | K19: 67.814 | S19: 115.831
A20: + Net Cash From Disc Ops | B20: CF_NET_CASH_DISCONT_OPS_OPER | C20: — | D20: — | E20: 0 | F20: 0 | G20: 0 | H20: 0 | I20: 0 | J20: 0 | K20: 0 | S20: 0
A21: Cash from Operating Activities | B21: CF_CASH_FROM_OPER | C21: 52.777 | D21: 39.746 | E21: 74.165 | F21: 129.529 | G21: 130.469 | H21: 133.778 | I21: 185.976 | J21: 226.899 | K21: 237.997 | S21: 246.029
A23: Cash from Investing Activities
A24: + Change in Fixed & Intang | B24: CHG_IN_FXD_&_INTANG_AST_DETAILED | C24: -7.429 | D24: -14.145 | E24: -7.192 | F24: -18.031 | G24: -30.309 | H24: -38.333 | I24: -19.412 | J24: -24.092 | K24: -53.451 | S24: -73.156
A25: + Disp in Fixed & Intang | B25: DISP_FXD_&_INTANGIBLES_DETAILED | C25: 0 | D25: 0.189 | E25: 0 | F25: 0 | G25: 0.095 | H25: 0 | I25: 0 | J25: 0 | K25: 0 | S25: 0
A26: + Disp of Fixed Prod Assets | B26: CF_DISPOSAL_OF_FIXED_PROD_ASSETS | C26: — | D26: — | E26: — | F26: — | G26: 0.095 | H26: — | I26: — | J26: — | K26: 0 | S26: 0
A27: + Disp of Intangible Assets | B27: CF_DISPOSAL_OF_INTANGIBLE_ASSETS | C27: — | D27: — | E27: 0 | F27: 0 | G27: 0 | H27: 0 | I27: 0 | J27: 0 | K27: 0 | S27: 0
A28: + Acq of Fixed & Intang | B28: ACQUIS_FXD_&_INTANG_DETAILED | C28: -7.429 | D28: -14.334 | E28: -7.192 | F28: -18.031 | G28: -30.404 | H28: -38.333 | I28: -19.412 | J28: -24.092 | K28: -53.451 | S28: -73.156
A29: + Acq of Fixed Prod Assets | B29: CF_PURCHASE_OF_FIXED_PROD_ASSETS | C29: — | D29: — | E29: -7.192 | F29: -18.031 | G29: -30.404 | H29: -38.333 | I29: -19.412 | J29: -24.092 | K29: -53.451 | L29: =L30*'ALGN(IS)'!L$6 -> -48.615445 | M29: =M30*'ALGN(IS)'!M$6 -> -55.907762 | N29: =N30*'ALGN(IS)'!N$6 -> -62.616693 | O29: =O30*'ALGN(IS)'!O$6 -> -68.878362 | P29: =P30*'ALGN(IS)'!P$6 -> -75.766199 | S29: -73.156
A30: % revenu | C30: =C29/'ALGN(IS)'!C$6 -> #VALUE! | D30: =D29/'ALGN(IS)'!D$6 -> #VALUE! | E30: =E29/'ALGN(IS)'!E$6 -> -0.023026705 | F30: =F29/'ALGN(IS)'!F$6 -> -0.046576567 | G30: =G29/'ALGN(IS)'!G$6 -> -0.063375863 | H30: =H29/'ALGN(IS)'!H$6 -> -0.068446774 | I30: =I29/'ALGN(IS)'!I$6 -> -0.029402944 | J30: =J29/'ALGN(IS)'!J$6 -> -0.031631202 | K30: =K29/'ALGN(IS)'!K$6 -> -0.063219261 | L30: -0.05 | M30: -0.05 | N30: -0.05 | O30: -0.05 | P30: -0.05 | Q30: =(K29/G29)^(1/5)-1 -> 0.11945083 | R30: =AVERAGE(G30:K30) -> -0.051215209
A31: + Acq of Intangible Assets | B31: CF_ACQUISITION_OF_INTANG_ASSETS | C31: — | D31: — | E31: 0 | F31: 0 | G31: 0 | H31: 0 | I31: 0 | J31: 0 | K31: 0 | S31: 0
A32: + Net Change in LT Investment | B32: NET_CHG_IN_LT_INVEST_DETAILED | C32: 0 | D32: 0 | E32: 0 | F32: 0 | G32: 0 | H32: 0 | I32: 0 | J32: 0 | K32: 0 | S32: 0
A33: + Dec in LT Investment | B33: CF_DECR_INVEST | C33: 0 | D33: 0 | E33: 0 | F33: 0 | G33: 0 | H33: 0 | I33: 0 | J33: 0 | K33: 0 | S33: 0
A34: + Inc in LT Investment | B34: CF_INCR_INVEST | C34: 0 | D34: 0 | E34: 0 | F34: 0 | G34: 0 | H34: 0 | I34: 0 | J34: 0 | K34: 0 | S34: 0
A35: + Net Cash From Acq & Div | B35: CF_NT_CSH_RCVD_PD_FOR_ACQUIS_DIV | C35: — | D35: — | E35: 0 | F35: 0 | G35: -187.588 | H35: 0 | I35: -7.652 | J35: 0 | K35: 0 | S35: 0
A36: + Cash from Divestitures | B36: CF_CASH_FOR_DIVESTITURES | C36: — | D36: — | E36: 0 | F36: 0 | G36: 0 | H36: 0 | I36: 0 | J36: 0 | K36: 0 | S36: 0
A37: + Cash for Acq of Subs | B37: CF_CASH_FOR_ACQUIS_SUBSIDIARIES | C37: — | D37: — | E37: 0 | F37: 0 | G37: -187.588 | H37: 0 | I37: -7.652 | J37: 0 | K37: 0 | S37: 0
A38: + Cash for JVs | B38: CF_CASH_FOR_JOINT_VENTURES_ASSOC | C38: — | D38: — | E38: 0 | F38: 0 | G38: 0 | H38: 0 | I38: 0 | J38: 0 | K38: 0 | S38: 0
A39: + Other Investing Activities | B39: OTHER_INVESTING_ACT_DETAILED | C39: -29.35 | D39: 13.09 | E39: 5.636 | F39: 2.111 | G39: 6.291 | H39: -39.967 | I39: -183.67 | J39: -177.535 | K39: -112.91 | S39: 142.279
A40: + Net Cash From Disc Ops | B40: CF_NET_CASH_DISCONTINUED_OPS_INV | C40: — | D40: — | E40: 0 | F40: 0 | G40: 0 | H40: 0 | I40: 0 | J40: 0 | K40: 0 | S40: 0
A41: Cash from Investing Activities | B41: CF_CASH_FROM_INV_ACT | C41: -36.779 | D41: -1.055 | E41: -1.556 | F41: -15.92 | G41: -211.606 | H41: -78.3 | I41: -210.734 | J41: -201.627 | K41: -166.361 | S41: 69.122998
A43: Cash from Financing Activities
A44: + Dividends Paid | B44: CF_DVD_PAID | C44: 0 | D44: 0 | E44: 0 | F44: 0 | G44: 0 | H44: 0 | I44: 0 | J44: 0 | K44: 0 | S44: 0
A45: + Cash From (Repayment) Debt | B45: PROC_FR_REPAYMNTS_BOR_DETAILED | C45: -11.5 | D45: -0.407 | E45: -0.136 | F45: 0 | G45: 0 | H45: 0 | I45: 0 | J45: 0 | K45: 0 | S45: 0
A46: + Cash From (Repay) ST Debt | B46: CF_NET_CHG_IN_ST_DBT_&_CPTL_LEAS | C46: — | D46: — | E46: -0.136 | F46: — | G46: — | H46: — | I46: — | J46: — | K46: 0 | S46: 0
A47: + Cash From LT Debt | B47: CF_PROC_LT_DEBT_&_CAPITAL_LEASE | C47: — | D47: — | E47: — | F47: — | G47: — | H47: — | I47: — | J47: — | K47: 0 | S47: 0
A48: + Repayments of LT Debt | B48: CF_PYMT_LT_DEBT_&_CAPITAL_LEASE | C48: — | D48: — | E48: — | F48: — | G48: — | H48: — | I48: — | J48: — | K48: 0 | S48: 0
A49: + Cash (Repurchase) of Equity | B49: PROC_FR_REPURCH_EQTY_DETAILED | C49: 29.442 | D49: -39.488 | E49: 7.46 | F49: 15.787 | G49: 29.138 | H49: 12.311 | I49: -33.808 | J49: -58.812 | K49: -80.07 | S49: -40.043
A50: + Increase in Capital Stock | B50: CF_INCR_CAP_STOCK | C50: 29.442 | D50: 10.65 | E50: 7.46 | F50: 15.787 | G50: 36.892 | H50: 59.514 | I50: 61.299 | J50: 39.421 | K50: 21.721 | S50: 29.318999
A51: + Decrease in Capital Stock | B51: CF_DECR_CAP_STOCK | C51: 0 | D51: -50.138 | E51: 0 | F51: 0 | G51: -7.754 | H51: -47.203 | I51: -95.107 | J51: -98.233 | K51: -101.791 | S51: -69.362
A52: + Other Financing Activities | B52: CF_OTHER_FINANCING_ACT_EXCL_FX | C52: — | D52: — | E52: -0.487 | F52: -1.08 | G52: -1.897 | H52: -2.106 | I52: -4.363 | J52: -7.608 | K52: -20.716 | S52: -29.407
A53: + Net Cash From Disc Ops | B53: CF_NET_CASH_DISCONTINUED_OPS_FIN | C53: — | D53: — | E53: 0 | F53: 0 | G53: 0 | H53: 0 | I53: 0 | J53: 0 | K53: 0 | S53: 0
A54: Cash from Financing Activities | B54: CFF_ACTIVITIES_DETAILED | C54: 18.008 | D54: -40.71 | E54: 6.837 | F54: 14.707 | G54: 27.241 | H54: 10.205 | I54: -38.171 | J54: -66.42 | K54: -100.786 | S54: -69.45
A56: Effect of Foreign Exchange Rates | B56: CF_EFFECT_FOREIGN_EXCHANGES | C56: — | D56: — | E56: -0.059 | F56: -0.139 | G56: -0.093 | H56: 0.028 | I56: -0.504 | J56: -1.934 | K56: -3.007 | S56: 0.206
A58: Net Changes in Cash | B58: CF_NET_CHNG_CASH | C58: 34.006 | D58: -2.019 | E58: 79.387 | F58: 128.177 | G58: -53.989 | H58: 65.711 | I58: -63.433 | J58: -43.082 | K58: -32.157 | S58: 245.908
A60: Cash Paid for Taxes | B60: CF_CASH_PAID_FOR_TAX | C60: 1.632 | D60: 1.51 | E60: 2.004 | F60: 1.894 | G60: 0.051 | H60: 2.825 | I60: 4.125 | J60: 5.666 | K60: 40.621
A61: Cash Paid for Interest | B61: CF_ACT_CASH_PAID_FOR_INT_DEBT | C61: 0.415 | D61: 0 | E61: 0.084 | F61: 0.019 | G61: 1.953 | H61: 0.027 | I61: — | J61: — | K61: —
A63: Reference Items
A64: EBITDA | B64: EBITDA | C64: 45.444 | D64: 34.536 | E64: -21.008 | F64: 116.92 | G64: 107.837 | H64: 103.403 | I64: 111.037 | J64: 211.432 | K64: 206.638 | S64: 261.537
A65: Trailing 12M EBITDA Margin | B65: EBITDA_MARGIN | C65: 15.982724 | D65: 11.361423 | E65: -6.726154 | F65: 30.202053 | G65: 22.478171 | H65: 18.46347 | I65: 16.818538 | J65: 27.759623 | K65: 24.440144 | S65: 25.717859
A66: Net Cash Paid for Acquisitions | B66: CF_NET_CASH_PAID_FOR_AQUIS | C66: — | D66: — | E66: — | F66: — | G66: 187.588 | H66: — | I66: 7.652 | J66: 0 | K66: 0 | S66: 0
A67: Tax Benefit from Stock Options | B67: CF_TAX_BENEFIT_FRM_STOCK_OPTIONS | C67: 0.449 | D67: 0.144 | E67: -0.637 | F67: 3.965 | G67: 11.391 | H67: 17.187 | I67: 27.103 | J67: 21.393 | K67: 10.396 | S67: 15.676
A68: Free Cash Flow | B68: CF_FREE_CASH_FLOW | C68: 45.348 | D68: 25.412 | E68: 66.973 | F68: 111.498 | G68: 100.065 | H68: 95.445 | I68: 166.564 | J68: 202.807 | K68: 184.546 | S68: 172.873
A69: Free Cash Flow to Firm | B69: CF_FREE_CASH_FLOW_FIRM | C69: 45.678652 | D69: — | E69: — | F69: 111.51183 | G69: 100.10283 | H69: — | I69: — | J69: — | K69: —
A70: Free Cash Flow to Equity | B70: FREE_CASH_FLOW_EQUITY | C70: 33.848 | D70: 25.194 | E70: 66.837 | F70: 111.498 | G70: 100.16 | H70: 95.445 | I70: 166.564 | J70: 202.807 | K70: 184.546 | S70: 172.873
A71: Free Cash Flow per Basic Share | B71: FREE_CASH_FLOW_PER_SH | C71: 0.675063 | D71: 0.380351 | E71: 0.969303 | F71: 1.470465 | G71: 1.283082 | H71: 1.185225 | I71: 2.067808 | J71: 2.511417 | K71: 2.306883 | S71: 2.1668886
A72: Price to Free Cash Flow | B72: PX_TO_FREE_CASH_FLOW | C72: 24.708822 | D72: 23.005076 | E72: 18.38435 | F72: 13.288315 | G72: 18.490634 | H72: 23.413272 | I72: 27.633127 | J72: 22.262329 | K72: 28.545015 | S72: 43.384787
A73: Cash Flow to Net Income | B73: CASH_FLOW_TO_NET_INC | C73: 1.477354 | D73: 0.496906 | E73: — | F73: 1.744428 | G73: 1.955588 | H73: 2.279361 | I73: 2.892542 | J73: 1.555893 | K73: 1.652527 | S73: 1.1646972
A74: Source: Bloomberg

Sheet ALGN(BS)
A2: Align Technology Inc (ALGN US) - Standardized
A4: In Millions of USD except Per Share | C4: Q4 2013 | D4: Q1 2014 | E4: Q2 2014 | F4: Q3 2014 | G4: Q4 2014 | H4: Q1 2015 | I4: Q2 2015 | J4: Q3 2015 | K4: Q4 2015 | L4: Q1 2016 | M4: Q2 2016 | N4: Q3 2016
A5: 3 Months Ending | C5: 12/31/2013 | D5: 03/31/2014 | E5: 06/30/2014 | F5: 09/30/2014 | G5: 12/31/2014 | H5: 03/31/2015 | I5: 06/30/2015 | J5: 09/30/2015 | K5: 12/31/2015 | L5: 03/31/2016 | M5: 06/30/2016 | N5: 09/30/2016
A6: Total Assets
A7: + Cash, Cash Equivalents & STI | B7: C&CE_AND_STI_DETAILED | C7: 369.993 | D7: 366.443 | E7: 365.53 | F7: 425.496 | G7: 454.658 | H7: 444.801 | I7: 438.542 | J7: 484.755 | K7: 527.295 | L7: 548.078 | M7: 571.813 | N7: 612.966
A8: + Cash & Cash Equivalents | B8: BS_CASH_NEAR_CASH_ITEM | C8: 242.953 | D8: 182.766 | E8: 167.471 | F8: 180.676 | G8: 199.871 | H8: 189.978 | I8: 161.753 | J8: 174.04 | K8: 167.714 | L8: 154.418 | M8: 167.706 | N8: 419.948
A9: + ST Investments | B9: BS_MKT_SEC_OTHER_ST_INVEST | C9: 127.04 | D9: 183.677 | E9: 198.059 | F9: 244.82 | G9: 254.787 | H9: 254.823 | I9: 276.789 | J9: 310.715 | K9: 359.581 | L9: 393.66 | M9: 404.107 | N9: 193.018
A10: + Accounts & Notes Receiv | B10: BS_ACCT_NOTE_RCV | C10: 113.25 | D10: 126.183 | E10: 131.028 | F10: 130.047 | G10: 129.751 | H10: 138.159 | I10: 146.466 | J10: 148.395 | K10: 158.55 | L10: 178 | M10: 192.66 | N10: 244.992
A11: + Accounts Receivable, Net | B11: BS_ACCTS_REC_EXCL_NOTES_REC | C11: 113.25 | D11: 126.183 | E11: 131.028 | F11: 130.047 | G11: 129.751 | H11: 138.159 | I11: 146.466 | J11: 148.395 | K11: 158.55 | L11: 178 | M11: 192.66 | N11: 244.992
A12: + Notes Receivable, Net | B12: NOTES_RECEIVABLE | C12: 0 | D12: 0 | E12: 0 | F12: 0 | G12: 0 | H12: 0 | I12: 0 | J12: 0 | K12: 0 | L12: 0 | M12: 0 | N12: 0
A13: + Inventories | B13: BS_INVENTORIES | C13: 13.968 | D13: 15.84 | E13: 13.115 | F13: 15.983 | G13: 15.928 | H13: 14.572 | I13: 16.415 | J13: 18.939 | K13: 19.465 | L13: 22.618 | M13: 22.992 | N13: 26.341
A14: + Raw Materials | B14: INVTRY_RAW_MATERIALS | C14: 5.172 | D14: 5.962 | E14: 3.493 | F14: 6.24 | G14: 8.143 | H14: 5.99 | I14: 7.352 | J14: 9.69 | K14: 9.95 | L14: 9.676 | M14: 8.217 | N14: 12.018
A15: + Work In Process | B15: INVTRY_IN_PROGRESS | C15: 4.241 | D15: 3.592 | E15: 3.43 | F15: 3.734 | G15: 2.97 | H15: 4.487 | I15: 5.243 | J15: 6.659 | K15: 7.067 | L15: 9.939 | M15: 10.889 | N15: 1.488
A16: + Finished Goods | B16: INVTRY_FINISHED_GOODS | C16: 4.555 | D16: 6.286 | E16: 6.192 | F16: 6.009 | G16: 4.815 | H16: 4.095 | I16: 3.82 | J16: 2.59 | K16: 2.448 | L16: 3.003 | M16: 3.886 | N16: 12.835
A17: + Other Inventory | B17: BS_OTHER_INV | C17: 0 | D17: 0 | E17: 0 | F17: 0 | G17: 0 | H17: 0 | I17: 0 | J17: 0 | K17: 0 | L17: 0 | M17: 0 | N17: 0
A18: + Other ST Assets | B18: OTHER_CURRENT_ASSETS_DETAILED | C18: 47.465 | D18: 43.711 | E18: 44.839 | F18: 44.146 | G18: 56.823 | H18: 59.78 | I18: 56.483 | J18: 59.644 | K18: 26.7 | L18: 34.307 | M18: 37.942 | N18: 27.469
A19: + Derivative & Hedging Assets | B19: BS_DERIV_&_HEDGING_ASSETS_ST | C19: 0 | D19: — | E19: — | F19: — | G19: 0 | H19: — | I19: — | J19: — | K19: 0 | L19: — | M19: — | N19: —
A20: + Deferred Tax Assets | B20: BS_DEFERRED_TAX_ASSETS_ST | C20: — | D20: — | E20: — | F20: — | G20: 37.053 | H20: 29.911 | I20: 29.972 | J20: 30.09 | K20: 0 | L20: — | M20: — | N20: —
A21: + Misc ST Assets | B21: BS_OTHER_CUR_ASSET_LESS_PREPAY | C21: 47.465 | D21: 43.711 | E21: 44.839 | F21: 44.146 | G21: 19.77 | H21: 29.869 | I21: 26.511 | J21: 29.554 | K21: 26.7 | L21: 34.307 | M21: 37.942 | N21: 27.469
A22: Total Current Assets | B22: BS_CUR_ASSET_REPORT | C22: 544.676 | D22: 552.177 | E22: 554.512 | F22: 615.672 | G22: 657.16 | H22: 657.312 | I22: 657.906 | J22: 711.733 | K22: 732.01 | L22: 783.003 | M22: 825.407 | N22: 911.768
A23: + Property, Plant & Equip, Net | B23: BS_NET_FIX_ASSET | C23: 75.743 | D23: 79.093 | E23: 81.312 | F23: 86.447 | G23: 90.125 | H23: 99.764 | I23: 108.029 | J23: 120.738 | K23: 136.473 | L23: 148.029 | M23: 161.685 | N23: 172.658
A24: + Property, Plant & Equip | B24: BS_GROSS_FIX_ASSET | C24: 181.249 | D24: — | E24: — | F24: — | G24: 197.927 | H24: — | I24: — | J24: — | K24: 254.51 | L24: — | M24: — | N24: —
A25: - Accumulated Depreciation | B25: BS_ACCUM_DEPR | C25: 105.506 | D25: — | E25: — | F25: — | G25: 107.802 | H25: — | I25: — | J25: — | K25: 118.037 | L25: — | M25: — | N25: —
A26: + LT Investments & Receivables | B26: BS_LT_INVEST | C26: 101.978 | D26: 138.929 | E26: 137.148 | F26: 136.017 | G26: 147.892 | H26: 168.171 | I26: 158.161 | J26: 145.246 | K26: 151.37 | L26: 132.69 | M26: 113.158 | N26: 62.82
A27: + LT Marketable Securities | B27: BS_LT_MARKETABLE_SECURITIES | C27: 101.978 | D27: 138.929 | E27: 137.148 | F27: 136.017 | G27: 147.892 | H27: 168.171 | I27: 158.161 | J27: 145.246 | K27: 151.37 | L27: 132.69 | M27: 113.158 | N27: 62.82
A28: + Other LT Assets | B28: BS_OTHER_ASSETS_DEF_CHRG_OTHER | C28: 109.75 | D28: 115.442 | E28: 112.461 | F28: 48.564 | G28: 92.82 | H28: 103.158 | I28: 104.485 | J28: 101.845 | K28: 138.78 | L28: 143.838 | M28: 151.023 | N28: 211.647
A29: + Total Intangible Assets | B29: BS_DISCLOSED_INTANGIBLES | C29: 85.362 | D29: 84.388 | E29: 83.795 | F29: 82.926 | G29: 82.056 | H29: 81.274 | I29: 80.59 | J29: 79.715 | K29: 79.162 | L29: 78.606 | M29: 83.749 | N29: 82.987
A30: + Goodwill | B30: BS_GOODWILL | C30: 61.623 | D30: 61.751 | E30: 61.807 | F30: 61.589 | G30: 61.369 | H30: 61.237 | I30: 61.203 | J30: 60.978 | K30: 61.074 | L30: 61.168 | M30: 61.119 | N30: 61.195
A31: + Other Intangible Assets | B31: OTHER_INTANGIBLE_ASSETS_DETAILED | C31: 23.739 | D31: 22.637 | E31: 21.988 | F31: 21.337 | G31: 20.687 | H31: 20.037 | I31: 19.387 | J31: 18.737 | K31: 18.088 | L31: 17.438 | M31: 22.63 | N31: 21.792
A32: + Deferred Tax Assets | B32: BS_DEFERRED_TAX_ASSETS_LT | C32: 15.766 | D32: 22.739 | E32: 20.456 | F32: 19.714 | G32: 3.099 | H32: 14.63 | I32: 16.014 | J32: 14.542 | K32: 51.416 | L32: 57.527 | M32: 60.051 | N32: 68.918
A33: + Derivative & Hedging Assets | B33: BS_DERIV_&_HEDGING_ASSETS_LT | C33: 0 | D33: — | E33: — | F33: — | G33: 0 | H33: — | I33: — | J33: — | K33: 0 | L33: — | M33: — | N33: —
A34: + Investments in Affiliates | B34: BS_INVEST_IN_ASSOC_CO | C34: — | D34: — | E34: — | F34: — | G34: — | H34: — | I34: — | J34: — | K34: — | L34: — | M34: — | N34: 46.268
A35: + Misc LT Assets | B35: OTHER_NONCURRENT_ASSETS_DETAILED | C35: 8.622 | D35: 8.315 | E35: 8.21 | F35: 7.513 | G35: 7.665 | H35: 7.254 | I35: 7.881 | J35: 7.588 | K35: 8.202 | L35: 7.705 | M35: 7.223 | N35: 13.474
A36: Total Noncurrent Assets | B36: BS_TOT_NON_CUR_ASSET | C36: 287.471 | D36: 333.464 | E36: 330.921 | F36: 271.028 | G36: 330.837 | H36: 371.093 | I36: 370.675 | J36: 367.829 | K36: 426.623 | L36: 424.557 | M36: 425.866 | N36: 447.125
A37: Total Assets | B37: BS_TOT_ASSET | C37: 832.147 | D37: 885.641 | E37: 885.433 | F37: 948.289 | G37: 987.997 | H37: 1028.405 | I37: 1028.581 | J37: 1079.562 | K37: 1158.633 | L37: 1207.56 | M37: 1251.273 | N37: 1358.893
A39: Liabilities & Shareholders' Equity
A40: + Payables & Accruals | B40: ACCT_PAYABLE_&_ACCRUALS_DETAILED | C40: 98.063 | D40: 89.855 | E40: 101.988 | F40: 111.117 | G40: 111.127 | H40: 106.707 | I40: 121.505 | J40: 128.513 | K40: 142.119 | L40: 128.981 | M40: 138.432 | N40: 165.642
A41: + Accounts Payable | B41: BS_ACCT_PAYABLE | C41: 17.718 | D41: 18.506 | E41: 20.939 | F41: 24.517 | G41: 23.247 | H41: 24.996 | I41: 29.513 | J41: 32.599 | K41: 34.354 | L41: 36.258 | M41: 30.927 | N41: 33.104
A42: + Accrued Taxes | B42: BS_TAXES_PAYABLE | C42: 0 | D42: — | E42: 8.695 | F42: — | G42: 0 | H42: — | I42: 1.939 | J42: 2.4 | K42: 2.646 | L42: 1.793 | M42: 3.385 | N42: 5.043
A43: + Interest & Dividends Payable | B43: BS_INTEREST_&_DIVIDENDS_PAYABLE | C43: 0 | D43: — | E43: — | F43: — | G43: 0 | H43: — | I43: — | J43: — | K43: 0 | L43: — | M43: — | N43: —
A44: + Other Payables & Accruals | B44: BS_ACCRUAL | C44: 80.345 | D44: 71.349 | E44: 72.354 | F44: 86.6 | G44: 87.88 | H44: 81.711 | I44: 90.053 | J44: 93.514 | K44: 105.119 | L44: 90.93 | M44: 104.12 | N44: 127.495
A45: + ST Debt | B45: BS_ST_BORROW | C45: 0 | D45: 0 | E45: 0 | F45: 0 | G45: 0 | H45: 0 | I45: 0 | J45: 0 | K45: 0 | L45: 0 | M45: 0 | N45: 0
A46: + ST Borrowings | B46: SHORT_TERM_DEBT_DETAILED | C46: 0 | D46: 0 | E46: 0 | F46: — | G46: 0 | H46: 0 | I46: 0 | J46: 0 | K46: 0 | L46: 0 | M46: 0 | N46: 0
A47: + ST Capital Leases | B47: ST_CAPITAL_LEASE_OBLIGATIONS | C47: 0 | D47: — | E47: — | F47: — | G47: 0 | H47: — | I47: — | J47: — | K47: 0 | L47: — | M47: — | N47: —
A48: + Other ST Liabilities | B48: OTHER_CURRENT_LIABS_SUB_DETAILED | C48: 77.275 | D48: 81 | E48: 85.125 | F48: 87.443 | G48: 90.684 | H48: 93.868 | I48: 101.42 | J48: 115.998 | K48: 129.553 | L48: 145.769 | M48: 160.557 | N48: 177.409
A49: + Deferred Revenue | B49: ST_DEFERRED_REVENUE | C49: 77.275 | D49: 81 | E49: 85.125 | F49: 87.443 | G49: 90.684 | H49: 93.868 | I49: 101.42 | J49: 115.998 | K49: 129.553 | L49: 145.769 | M49: 160.557 | N49: 177.409
A50: + Derivatives & Hedging | B50: BS_DERIVATIVE_&_HEDGING_LIABS_ST | C50: 0 | D50: — | E50: — | F50: — | G50: 0 | H50: — | I50: — | J50: — | K50: — | L50: — | M50: — | N50: —
A51: + Misc ST Liabilities | B51: OTHER_CURRENT_LIABS_DETAILED | C51: 0 | D51: 0 | E51: 0 | F51: 0 | G51: 0 | H51: 0 | I51: 0 | J51: 0 | K51: 0 | L51: 0 | M51: 0 | N51: 0
A52: Total Current Liabilities | B52: BS_CUR_LIAB | C52: 175.338 | D52: 170.855 | E52: 187.113 | F52: 198.56 | G52: 201.811 | H52: 200.575 | I52: 222.925 | J52: 244.511 | K52: 271.672 | L52: 274.75 | M52: 298.989 | N52: 343.051
A53: + LT Debt | B53: BS_LT_BORROW | C53: 0 | D53: 0 | E53: 0 | F53: 0 | G53: 0 | H53: 0 | I53: 0 | J53: 0 | K53: 0 | L53: 0 | M53: 0 | N53: 0
A54: + LT Borrowings | B54: LONG_TERM_BORROWINGS_DETAILED | C54: 0 | D54: 0 | E54: 0 | F54: 0 | G54: 0 | H54: 0 | I54: 0 | J54: 0 | K54: 0 | L54: 0 | M54: 0 | N54: 0
A55: + LT Capital Leases | B55: LT_CAPITAL_LEASE_OBLIGATIONS | C55: 0 | D55: — | E55: — | F55: — | G55: 0 | H55: — | I55: — | J55: — | K55: 0 | L55: — | M55: — | N55: —
A56: + Other LT Liabilities | B56: OTHER_NONCUR_LIABS_SUB_DETAILED | C56: 22.839 | D56: 18.033 | E56: 22.524 | F56: 27.273 | G56: 33.415 | H56: 34.296 | I56: 35.855 | J56: 36.792 | K56: 39.035 | L56: 40.78 | M56: 42.426 | N56: 43.532
A57: + Accrued Liabilities | B57: BS_ACCRUED_LIABILITIES | C57: 0 | D57: — | E57: — | F57: — | G57: 0 | H57: — | I57: — | J57: — | K57: 0 | L57: — | M57: — | N57: —
A58: + Pension Liabilities | B58: PENSION_LIABILITIES | C58: 0 | D58: — | E58: — | F58: — | G58: 0 | H58: — | I58: — | J58: — | K58: 0 | L58: — | M58: — | N58: —
A59: + Pensions | B59: BS_PENSIONS_LT_LIABS | C59: 0 | D59: — | E59: — | F59: — | G59: 0 | H59: — | I59: — | J59: — | K59: 0 | L59: — | M59: — | N59: —
A60: + Other Post-Ret Benefits | B60: BS_OPRB_LT_LIABS | C60: 0 | D60: — | E60: — | F60: — | G60: 0 | H60: — | I60: — | J60: — | K60: 0 | L60: — | M60: — | N60: —
A61: + Deferred Revenue | B61: LT_DEFERRED_REVENUE | C61: 0 | D61: — | E61: — | F61: — | G61: 0 | H61: — | I61: — | J61: — | K61: 0 | L61: — | M61: — | N61: —
A62: + Derivatives & Hedging | B62: BS_DERIVATIVE_&_HEDGING_LIABS_LT | C62: 0 | D62: — | E62: — | F62: — | G62: 0 | H62: — | I62: — | J62: — | K62: 0 | L62: — | M62: — | N62: —
A63: + Misc LT Liabilities | B63: OTHER_NONCURRENT_LIABS_DETAILED | C63: 22.839 | D63: 18.033 | E63: 22.524 | F63: 27.273 | G63: 33.415 | H63: 34.296 | I63: 35.855 | J63: 36.792 | K63: 39.035 | L63: 40.78 | M63: 42.426 | N63: 43.532
A64: Total Noncurrent Liabilities | B64: NON_CUR_LIAB | C64: 22.839 | D64: 18.033 | E64: 22.524 | F64: 27.273 | G64: 33.415 | H64: 34.296 | I64: 35.855 | J64: 36.792 | K64: 39.035 | L64: 40.78 | M64: 42.426 | N64: 43.532
A65: Total Liabilities | B65: BS_TOT_LIAB2 | C65: 198.177 | D65: 188.888 | E65: 209.637 | F65: 225.833 | G65: 235.226 | H65: 234.871 | I65: 258.78 | J65: 281.303 | K65: 310.707 | L65: 315.53 | M65: 341.415 | N65: 386.583
A66: + Preferred Equity | B66: BS_PFD_EQY | C66: 0 | D66: 0 | E66: 0 | F66: 0 | G66: 0 | H66: 0 | I66: 0 | J66: 0 | K66: 0 | L66: 0 | M66: 0 | N66: 0
A67: + Share Capital & APIC | B67: BS_SH_CAP_AND_APIC | C67: 729.586 | D67: 759.776 | E67: 742.894 | F67: 775.531 | G67: 783.418 | H67: 789.461 | I67: 775.814 | J67: 810.124 | K67: 821.515 | L67: 824.071 | M67: 821.823 | N67: 854.43
A68: + Common Stock | B68: BS_COMMON_STOCK | C68: 0.008 | D68: 0.008 | E68: 0.008 | F68: 0.008 | G68: 0.008 | H68: 0.008 | I68: 0.008 | J68: 0.008 | K68: 0.008 | L68: 0.008 | M68: 0.008 | N68: 0.008
A69: + Additional Paid in Capital | B69: BS_ADD_PAID_IN_CAP | C69: 729.578 | D69: 759.768 | E69: 742.886 | F69: 775.523 | G69: 783.41 | H69: 789.453 | I69: 775.806 | J69: 810.116 | K69: 821.507 | L69: 824.063 | M69: 821.815 | N69: 854.422
A70: - Treasury Stock | B70: BS_AMT_OF_TSY_STOCK | C70: 0 | D70: 0 | E70: 0 | F70: 0 | G70: 0 | H70: 0 | I70: 0 | J70: 0 | K70: 0 | L70: 0 | M70: 0 | N70: 0
A71: + Retained Earnings | B71: BS_PURE_RETAINED_EARNINGS | C71: -95.91 | D71: -63.465 | E71: -67.606 | F71: -53.135 | G71: -30.507 | H71: 4.179 | I71: -5.826 | J71: -11.89 | K71: 27.391 | L71: 67.937 | M71: 87.607 | N71: 117.965
A72: + Other Equity | B72: OTHER_INS_RES_TO_SHRHLDR_EQY | C72: 0.294 | D72: 0.442 | E72: 0.508 | F72: 0.06 | G72: -0.14 | H72: -0.106 | I72: -0.187 | J72: 0.025 | K72: -0.98 | L72: 0.022 | M72: 0.428 | N72: -0.085
A73: Equity Before Minority Interest | B73: EQTY_BEF_MINORITY_INT_DETAILED | C73: 633.97 | D73: 696.753 | E73: 675.796 | F73: 722.456 | G73: 752.771 | H73: 793.534 | I73: 769.801 | J73: 798.259 | K73: 847.926 | L73: 892.03 | M73: 909.858 | N73: 972.31
A74: + Minority/Non Controlling Interest | B74: MINORITY_NONCONTROLLING_INTEREST | C74: 0 | D74: 0 | E74: 0 | F74: 0 | G74: 0 | H74: 0 | I74: 0 | J74: 0 | K74: 0 | L74: 0 | M74: 0 | N74: 0
... A76: Total Liabilities & Equity | B76: TOT_LIAB_AND_EQY | C76: 832.147 | D76: 885.641 | E76: 885.433 | F76: 948.289 | G76: 987.997 | H76: 1028.405 | I76: 1028.581 | J76: 1079.562 | K76: 1158.633 | L76: 1207.56 | M76: 1251.273 | N76: 1358.893
A78: Reference Items
A79: Accounting Standard | B79: ACCOUNTING_STANDARD | C79: US GAAP | D79: US GAAP | E79: US GAAP | F79: US GAAP | G79: US GAAP | H79: US GAAP | I79: US GAAP | J79: US GAAP | K79: US GAAP | L79: US GAAP | M79: US GAAP | N79: US GAAP
A80: Shares Outstanding | B80: BS_SH_OUT | C80: 80.583 | D80: 81.632 | E80: 80.783 | F80: 80.516 | G80: 80.205 | H80: 80.734 | I80: 80.069 | J80: 79.564 | K80: 79.5 | L80: 80.175 | M80: 79.868 | N80: 79.867
A81: Number of Treasury Shares | B81: BS_NUM_OF_TSY_SH | C81: 0 | D81: 0 | E81: 0 | F81: 0 | G81: 0 | H81: 0 | I81: 0 | J81: 0 | K81: 0 | L81: 0 | M81: 0 | N81: 0
A82: Future Minimum Operating Lease Obligations | B82: BS_FUTURE_MIN_OPER_LEASE_OBLIG | C82: 28.273 | D82: 29.566 | E82: 27.352 | F82: 24.725 | G82: 24.046 | H82: 24.307 | I82: 24.118 | J82: 21.904 | K82: 19.75 | L82: 19.41 | M82: 17.342 | N82: 32.617
A83: Capital Leases - Total | B83: BS_TOTAL_CAPITAL_LEASES | C83: 0 | D83: — | E83: — | F83: — | G83: 0 | H83: — | I83: — | J83: — | K83: 0 | L83: — | M83: — | N83: —
A84: Options Granted During Period | B84: BS_OPTIONS_GRANTED | C84: 0 | D84: 0 | E84: 0 | F84: 0 | G84: 0 | H84: 0 | I84: 0 | J84: 0 | K84: 0 | L84: 0 | M84: 0 | N84: 0
A85: Options Outstanding at Period End | B85: BS_OPTIONS_OUTSTANDING | C85: 1.321 | D85: 0.848 | E85: 0.805 | F85: 0.719 | G85: 0.668 | H85: 0.64 | I85: 0.556 | J85: 0.539 | K85: 0.496 | L85: 0.466 | M85: 0.366 | N85: 0.272
A86: Net Debt | B86: NET_DEBT | C86: -471.971 | D86: -505.372 | E86: -502.678 | F86: -561.513 | G86: -602.55 | H86: -612.972 | I86: -596.703 | J86: -630.001 | K86: -678.665 | L86: -680.768 | M86: -684.971 | N86: -675.786
A87: Net Debt to Equity | B87: NET_DEBT_TO_SHRHLDR_EQTY | C87: -74.446898 | D87: -72.532447 | E87: -74.383098 | F87: -77.722796 | G87: -80.044263 | H87: -77.245839 | I87: -77.513929 | J87: -78.921879 | K87: -80.038234 | L87: -76.316716 | M87: -75.283286 | N87: -69.503142
A88: Tangible Common Equity Ratio | B88: TCE_RATIO | C88: 73.462643 | D88: 76.425923 | E88: 73.848919 | F88: 73.90309 | G88: 74.035174 | H88: 75.201846 | I88: 72.702272 | J88: 71.865395 | K88: 71.216735 | L88: 72.05112 | M88: 70.757346 | N88: 69.701295
A89: Current Ratio | B89: CUR_RATIO | C89: 3.106434 | D89: 3.231846 | E89: 2.963514 | F89: 3.100685 | G89: 3.256314 | H89: 3.277138 | I89: 2.951244 | J89: 2.910842 | K89: 2.694462 | L89: 2.849874 | M89: 2.76066 | N89: 2.657821
A90: Cash Conversion Cycle | B90: CASH_CONVERSION_CYCLE | C90: 49.16292 | D90: 54.743615 | E90: 46.811303 | F90: 45.797345 | G90: 47.631398 | H90: 48.842897 | I90: 44.407682 | J90: 42.551684 | K90: 43.362648 | L90: 46.805317 | M90: 50.190557 | N90: 57.179001
A91: Number of Employees | B91: NUM_OF_EMPLOYEES | C91: 3420 | D91: — | E91: — | F91: — | G91: 3580 | H91: — | I91: — | J91: — | K91: 4375 | L91: — | M91: — | N91: —
A92: Source: Bloomberg

Sheet DCF
A1: (1)_FCF Projections
A3: (in millions) | C3: 2004 | D3: 2005 | E3: 2006 | F3: 2007 | G3: 2008 | H3: 2009 | I3: 2010 | J3: 2011 | K3: 2012 | L3: 2013 | M3: 2014 | N3: 2015 | O3: 2016 | P3: 2017 | Q3: 2018 | R3: 2019 | S3: 2020 | T3: (NOTES:)
A4: Earnings Before Interest and Taxes | F4: ='ALGN(IS)'!C25 -> 32.059 | G4: ='ALGN(IS)'!D25 -> 21.745 | H4: ='ALGN(IS)'!E25 -> 36.98 | I4: ='ALGN(IS)'!F25 -> 98.617 | J4: ='ALGN(IS)'!G25 -> 101.472 | K4: ='ALGN(IS)'!H25 -> 124.234 | L4: ='ALGN(IS)'!I25 -> 161.225 | M4: ='ALGN(IS)'!J25 -> 193.576 | ... S4: ='ALGN(IS)'!P25 -> 359.88944 | V4: =(S4/O4)^(1/COUNT(O4:S4))-1 -> 0.092798894
A5: Effective Tax Rate | F5: 0.35 | G5: 0.23 | H5: 0.23 | I5: 0.23 | J5: 0.23 | K5: 0.23 | L5: 0.23 | M5: 0.23 | N5: 0.23 | O5: 0.23 | P5: 0.23 | Q5: 0.23 | R5: 0.23 | S5: 0.23
A6: x (1-Tax Rate) | C6: =C4*(1-C5) -> 0 | D6: =D4*(1-D5) -> 0 | E6: =E4*(1-E5) -> 0 | F6: =F4*(1-F5) -> 20.83835 | G6: =G4*(1-G5) -> 16.74365 | H6: =H4*(1-H5) -> 28.4746 | I6: =I4*(1-I5) -> 75.93509 | J6: =J4*(1-J5) -> 78.13344 | ... S6: =S4*(1-S5) -> 277.11487
A7: + Depreciation and Amortization | F7: ='ALGN(CF)'!C8 -> 13.385 | G7: ='ALGN(CF)'!D8 -> 12.791 | H7: ='ALGN(CF)'!E8 -> 13.004 | I7: ='ALGN(CF)'!F8 -> 14.186 | J7: ='ALGN(CF)'!G8 -> 17.477 | K7: ='ALGN(CF)'!H8 -> 17.811 | L7: ='ALGN(CF)'!I8 -> 16.825 | M7: ='ALGN(CF)'!J8 -> 17.856 | ... S7: ='ALGN(CF)'!P8 -> 30.306479
A8: - Capital Expenditures (FIX)*-1 | F8: 0 | G8: 0 | H8: ='ALGN(CF)'!E29*-1 -> 7.192 | I8: ='ALGN(CF)'!F29*-1 -> 18.031 | J8: ='ALGN(CF)'!G29*-1 -> 30.404 | K8: ='ALGN(CF)'!H29*-1 -> 38.333 | L8: ='ALGN(CF)'!I29*-1 -> 19.412 | M8: ='ALGN(CF)'!J29*-1 -> 24.092 | N8: ='ALGN(CF)'!K29*-1 -> 53.451 | O8: ='ALGN(CF)'!L29*-1 -> 48.615445 | ... S8: ='ALGN(CF)'!P29*-1 -> 75.766199
A9: - Change in Net Working Capital | F9: ='ALGN(CF)'!C14 -> -9.554 | G9: ='ALGN(CF)'!D14 -> -8.311 | H9: ='ALGN(CF)'!E14 -> 15.884 | I9: ='ALGN(CF)'!F14 -> 10.593 | J9: ='ALGN(CF)'!G14 -> 32.542 | K9: ='ALGN(CF)'!H14 -> -3.383 | L9: ='ALGN(CF)'!I14 -> 13.162 | M9: ='ALGN(CF)'!J14 -> 9.194 | ... S9: ='ALGN(CF)'!P14 -> 30.306479 | U9: Avg(5yr) | V9: CAGR(5yr)
A10: = Free Cash Flow | C10: =C6+C7-C8-C9 -> 0 | D10: =D6+D7-D8-D9 -> 0 | E10: =E6+E7-E8-E9 -> 0 | F10: =F6+F7-F8-F9 -> 43.77735 | G10: =G6+G7-G8-G9 -> 37.84565 | H10: =H6+H7-H8-H9 -> 18.4026 | I10: =I6+I7-I8-I9 -> 61.49709 | J10: =J6+J7-J8-J9 -> 32.66444 | ... S10: =S6+S7-S8-S9 -> 201.34867 | U10: =AVERAGE(O11:S11) -> 0.22211492 | V10: =(S10/O10)^(1/COUNT(O10:S10))-1 -> 0.092798894
A11: Growth yoy | D11: =(D10-C10)/C10 -> #DIV/0! | E11: =(E10-D10)/D10 -> #DIV/0! | F11: =(F10-E10)/E10 -> #DIV/0! | G11: =(G10-F10)/F10 -> -0.13549701 | H11: =(H10-G10)/G10 -> -0.51374597 | I11: =(I10-H10)/H10 -> 2.3417609 | J11: =(J10-I10)/I10 -> -0.46884576 | K11: =(K10-J10)/J10 -> 1.4038734 | ... S11: =(S10-R10)/R10 -> 0.1
A12: 3 year moving average | F12: =AVERAGE(D11:F11) -> #DIV/0! | G12: =AVERAGE(E11:G11) -> #DIV/0! | H12: =AVERAGE(F11:H11) -> #DIV/0! | I12: =AVERAGE(G11:I11) -> 0.56417266 | J12: =AVERAGE(H11:J11) -> 0.45305641 | K12: =AVERAGE(I11:K11) -> 1.0922629 | L12: =AVERAGE(J11:L11) -> 0.43849123 | M12: =AVERAGE(K11:M11) -> 0.67235805 | ... S12: =AVERAGE(Q11:S11) -> 0.10666667
A13: 5 year moving average | H13: =AVERAGE(D11:H11) -> #DIV/0! | I13: =AVERAGE(E11:I11) -> #DIV/0! | J13: =AVERAGE(F11:J11) -> #DIV/0! | K13: =AVERAGE(G11:K11) -> 0.52550913 | L13: =AVERAGE(H11:L11) -> 0.62869774 | M13: =AVERAGE(I11:M11) -> 0.77799787 | N13: =AVERAGE(J11:N11) -> 0.22751442 | O13: =AVERAGE(K11:O11) -> 0.44939849 | ... S13: =AVERAGE(O11:S11) -> 0.22211492
AC14: max | AD14: =MAX(Y24:AC38) -> 113.40162
AC15: min | AD15: =MIN(Y24:AC38) -> 70.785563
A16: (2)_WACC | Z16: EBITDA_5 vs. WACC | AC16: avg | AD16: =AVERAGE(Y24:AC38) -> 90.284223
Y17: =(Y18-$AA18)/$AA18 -> -0.19 | Z17: =(Z18-$AA18)/$AA18 -> -0.1 | AA17: =(AA18-$AA18)/$AA18 -> 0 | AB17: =(AB18-$AA18)/$AA18 -> 0.1 | AC17: =(AC18-$AA18)/$AA18 -> 0.21
A18: RF (10yr UST) | B18: 0.016 | S18: =B68 -> 92.452066 | T18: =U18*(1-10%) -> 1.866295e+08 | U18: =V18*(1-10%) -> 2.0736611e+08 | V18: =W18*(1-10%) -> 2.3040679e+08 | W18: =X18*(1-10%) -> 2.5600755e+08 | X18: =Y18*(1-10%) -> 2.8445283e+08 | Y18: =Z18*(1-10%) -> 3.160587e+08 | Z18: =AA18*(1-10%) -> 3.5117633e+08 | AA18: 3.9019592e+08 | AB18: =AA18*(1+10%) -> 4.2921552e+08 | AC18: =AB18*(1+10%) -> 4.7213707e+08 | AD18: =AC18*(1+10%) -> 5.1935077e+08 | AE18: =AD18*(1+10%) -> 5.7128585e+08 | AF18: =AE18*(1+10%) -> 6.2841444e+08
A19: RM | B19: 0.09 | R19: =(S19-S$30)/S$30 -> -0.25137112 | S19: =S20-0.25% -> 0.0819 | T19: 56.76555 | U19: 61.319709 | V19: 66.379885 | W19: 72.002303 | X19: 78.249434 | Y19: 85.190691 | Z19: 92.903199 | AA19: 101.47265 | AB19: 110.0421 | AC19: 119.4685 | AD19: 129.83754 | AE19: 141.24348 | AF19: 153.79002
A20: Beta2yr | B20: 1.1 | R20: =(S20-S$30)/S$30 -> -0.2285192 | S20: =S21-0.25% -> 0.0844 | T20: 56.23825 | U20: 60.740154 | V20: 65.742269 | W20: 71.300175 | X20: 77.475626 | Y20: 84.337239 | Z20: 91.961252 | AA20: 100.43238 | AB20: 108.9035 | AC20: 118.22174 | AD20: 128.47181 | AE20: 139.74688 | AF20: 152.14945
A21: Beta5yr | B21: 1.3 | R21: =(S21-S$30)/S$30 -> -0.20566728 | S21: =S22-0.25% -> 0.0869 | T21: 55.718025 | U21: 60.168392 | V21: 65.113244 | W21: 70.607524 | X21: 76.71228 | Y21: 83.495342 | Z21: 91.032077 | AA21: 99.406228 | AB21: 107.78038 | AC21: 116.99194 | AD21: 127.12467 | AE21: 138.27066 | AF21: 150.53125
A22: BetaAVG | B22: =SUM(B20:B21)/2 -> 1.2 | R22: =(S22-S$30)/S$30 -> -0.18281536 | S22: =S23-0.25% -> 0.0894 | T22: 55.204764 | U22: 59.6043 | V22: 64.492674 | W22: 69.9242 | X22: 75.95923 | Y22: 82.664818 | Z22: 90.115471 | AA22: 98.393975 | AB22: 106.67248 | AC22: 115.77883 | AD22: 125.79582 | AE22: 136.81451 | AF22: 148.93507
A23: CAPM (ke) | B23: =B18+B22*(B19-B18) -> 0.1048 | G23: Valuations: | R23: =(S23-S$30)/S$30 -> -0.15996344 | S23: =S24-0.25% -> 0.0919 | T23: 54.698357 | U23: 59.047758 | V23: 63.880425 | W23: 69.250056 | X23: 75.216312 | Y23: 81.845486 | Z23: 89.211234 | AA23: 97.395399 | AB23: 105.57956 | AC23: 114.58215 | AD23: 124.48499 | AE23: 135.37811 | AF23: 147.36054
A24: kd_pre | B24: 0 | G24: DCF _Perpetutiy | R24: =(S24-S$30)/S$30 -> -0.13711152 | S24: =S25-0.25% -> 0.0944 | T24: 54.198696 | U24: 58.498645 | V24: 63.276366 | W24: 68.584946 | X24: 74.483367 | Y24: 81.037169 | Z24: 88.319171 | AA24: 96.410285 | AB24: 104.5014 | AC24: 113.40162 | AD24: 123.19187 | AE24: 133.96114 | AF24: 145.80734 | AG24: =AVERAGE(Y24:AC24) -> 96.733929
A25: kd_post | B25: =B24*(1-N5) -> 0 | G25: Sensitivity_Analysis .P | R25: =(S25-S$30)/S$30 -> -0.1142596 | S25: =S26-0.25% -> 0.0969 | T25: 53.705675 | U25: 57.956846 | V25: 62.680369 | W25: 67.928728 | X25: 73.760239 | Y25: 80.239695 | Z25: 87.43909 | AA25: 95.438419 | AB25: 103.43775 | AC25: 112.23701 | AD25: 121.9162 | AE25: 132.5633 | AF25: 144.27512
A26: Shares Outstanding | B26: ='ALGN(BS)'!N80*1000000 -> 79867000 | R26: =(S26-S$30)/S$30 -> -0.091407678 | S26: =S27-0.25% -> 0.0994 | T26: 53.21919 | U26: 57.422245 | V26: 62.092307 | W26: 67.281264 | X26: 73.046772 | Y26: 79.452892 | Z26: 86.570802 | AA26: 94.479592 | AB26: 102.38838 | AC26: 111.08805 | AD26: 120.65769 | AE26: 131.18429 | AF26: 142.76355
A27: Current Price: | B27: 90.61 | G27: DCF _Growth | R27: =(S27-S$30)/S$30 -> -0.068555759 | S27: =S28-0.25% -> 0.1019 | T27: 52.73914 | U27: 56.894731 | V27: 61.512055 | W27: 66.642415 | X27: 72.342815 | Y27: 78.676592 | Z27: 85.714123 | AA27: 93.533601 | AB27: 101.35308 | AC27: 109.95451 | AD27: 119.41608 | AE27: 129.8238 | AF27: 141.2723
A28: ST Debt | B28: ='ALGN(BS)'!N45 -> 0 | G28: Sensitivity_Analysis .G | R28: =(S28-S$30)/S$30 -> -0.045703839 | S28: =S29-0.25% -> 0.1044 | T28: 52.265423 | U28: 56.374193 | V28: 60.939492 | W28: 66.012047 | X28: 71.648219 | Y28: 77.910633 | Z28: 84.86887 | AA28: 92.600244 | AB28: 100.33162 | AC28: 108.83613 | AD28: 118.19109 | AE28: 128.48155 | AF28: 139.80106
A29: LT Debt | B29: ='ALGN(BS)'!N53 -> 0 | R29: =(S29-S$30)/S$30 -> -0.02285192 | S29: =S30-0.25% -> 0.1069 | T29: 51.797943 | U29: 55.860522 | V29: 60.374498 | W29: 65.390028 | X29: 70.962839 | Y29: 77.154851 | Z29: 84.034864 | AA29: 91.679323 | AB29: 99.323782 | AC29: 107.73269 | AD29: 116.98248 | AE29: 127.15726 | AF29: 138.34951
A30: Total Debt | B30: 0 | C30: =B30/(B30+B31) -> 0 | G30: Dividend_Model | R30: =(S30-S$30)/S$30 -> 0 | S30: 0.1094 | T30: 51.336601 | U30: 55.353611 | V30: 59.816956 | W30: 64.776228 | X30: 70.28653 | Y30: 76.409088 | Z30: 83.211931 | AA30: 90.770644 | AB30: 98.329358 | AC30: 106.64394 | AD30: 115.78999 | AE30: 125.85063 | AF30: 136.91735
A31: Equity (Mkt Cap) | B31: =B26*B27 -> 7236748870 | C31: =1-C30 -> 1 | G31: Sensitivity_Analysis .D | R31: =(S31-S$30)/S$30 -> 0.02285192 | S31: =S30+0.25% -> 0.1119 | T31: 50.881303 | U31: 54.853356 | V31: 59.266749 | W31: 64.170519 | X31: 69.619153 | Y31: 75.67319 | Z31: 82.399897 | AA31: 89.874017 | AB31: 97.348137 | AC31: 105.56967 | AD31: 114.61335 | AE31: 124.56141 | AF31: 135.50427
R32: =(S32-S$30)/S$30 -> 0.045703839 | S32: =S31+0.25% -> 0.1144 | T32: 50.431955 | U32: 54.359655 | V32: 58.723765 | W32: 63.572777 | X32: 68.960567 | Y32: 74.947002 | Z32: 81.598595 | AA32: 88.989254 | AB32: 96.379914 | AC32: 104.50964 | AD32: 113.45234 | AE32: 123.2893 | AF32: 134.10997
A33: WACC | B33: =(B23*C31)+(B25*C30) -> 0.1048 | G33: Comparables_model | R33: =(S33-S$30)/S$30 -> 0.068555759 | S33: =S32+0.25% -> 0.1169 | T33: 49.988467 | U33: 53.872405 | V33: 58.187892 | W33: 62.982877 | X33: 68.310639 | Y33: 74.230374 | Z33: 80.807857 | AA33: 88.116172 | AB33: 95.424487 | AC33: 103.46363 | AD33: 112.30669 | AE33: 122.03406 | AF33: 132.73417
G34: SimSale_model | R34: =(S34-S$30)/S$30 -> 0.091407678 | S34: =S33+0.25% -> 0.1194 | T34: 49.550747 | U34: 53.391508 | V34: 57.65902 | W34: 62.4007 | X34: 67.669233 | Y34: 73.523159 | Z34: 80.027521 | AA34: 87.254589 | AB34: 94.481658 | AC34: 102.43143 | AD34: 111.17619 | AE34: 120.79542 | AF34: 131.37657
G35: Comp_EBITDA_model | R35: =(S35-S$30)/S$30 -> 0.1142596 | S35: =S34+0.25% -> 0.1219 | T35: 49.118708 | U35: 52.916866 | V35: 57.137042 | W35: 61.826126 | X35: 67.036219 | Y35: 72.825211 | Z35: 79.257425 | AA35: 86.404329 | AB35: 93.551234 | AC35: 101.41283 | AD35: 110.06058 | AE35: 119.57311 | AF35: 130.03689
A36: (3)_FCF_Perp/DCF/ValuePerShare | R36: =(S36-S$30)/S$30 -> 0.13711152 | S36: =S35+0.25% -> 0.1244 | T36: 48.692263 | U36: 52.448384 | V36: 56.621852 | W36: 61.259038 | X36: 66.411467 | Y36: 72.136389 | Z36: 78.497413 | AA36: 85.565217 | AB36: 92.633022 | AC36: 100.40761 | AD36: 108.95965 | AE36: 118.3669 | AF36: 128.71487
G37: Average_Value | R37: =(S37-S$30)/S$30 -> 0.15996344 | S37: =S36+0.25% -> 0.1269 | T37: 48.271326 | U37: 51.985967 | V37: 56.113346 | W37: 60.699323 | X37: 65.794852 | Y37: 71.456552 | Z37: 77.747329 | AA37: 84.737082 | AB37: 91.726835 | AC37: 99.415563 | AD37: 107.87316 | AE37: 117.17652 | AF37: 127.41022
A38: Perpetuity: (FCF(f)*(1+g))/(WACC-g) --> 0.5 to 4 | R38: =(S38-S$30)/S$30 -> 0.18281536 | S38: =S37+0.25% -> 0.1294 | T38: 47.855813 | U38: 51.529523 | V38: 55.611422 | W38: 60.146867 | X38: 65.186249 | Y38: 70.785563 | Z38: 77.007023 | AA38: 83.919756 | AB38: 90.832489 | AC38: 98.436495 | AD38: 106.8009 | AE38: 116.00175 | AF38: 126.12268
A39: Growth Rate Calc | B39: =V10 -> 0.092798894 | R39: =(S39-S$30)/S$30 -> 0.20566728 | S39: =S38+0.25% -> 0.1319 | T39: 47.445642 | U39: 51.07896 | V39: 55.115981 | W39: 59.601559 | X39: 64.585535 | Y39: 70.123286 | Z39: 76.276343 | AA39: 83.113072 | AB39: 89.949802 | AC39: 97.470205 | AD39: 105.74265 | AE39: 114.84233 | AF39: 124.85199
A40: Growth Rate Adj | B40: 0.02 | R40: =(S40-S$30)/S$30 -> 0.2285192 | S40: =S39+0.25% -> 0.1344 | T40: 47.040732 | U40: 50.634191 | V40: 54.626923 | W40: 59.063292 | X40: 63.992591 | Y40: 69.469589 | Z40: 75.555143 | AA40: 82.31687 | AB40: 89.078597 | AC40: 96.516496 | AD40: 104.69819 | AE40: 113.69804 | AF40: 123.59789
A41: Terminal Value | B41: =((S10*1000000)*(1+B40))/(B33-B40) -> 2.4218826e+09 | R41: =(S41-S$30)/S$30 -> 0.25137112 | S41: =S40+0.25% -> 0.1369 | T41: 46.641004 | U41: 50.195127 | V41: 54.144152 | W41: 58.531958 | X41: 63.407298 | Y41: 68.824342 | Z41: 74.84328 | AA41: 81.530989 | AB41: 88.218698 | AC41: 95.575178 | AD41: 103.66731 | AE41: 112.56865 | AF41: 122.36012
A42: Terminal Value/share | B42: =B41/B26 -> 30.323946 | R42: =(S42-S$30)/S$30 -> 0.27422303 | S42: =S41+0.25% -> 0.1394 | T42: 46.246379 | U42: 49.761681 | V42: 53.667573 | W42: 58.007452 | X42: 62.82954 | Y42: 68.187416 | Z42: 74.140612 | AA42: 80.755273 | AB42: 87.369935 | AC42: 94.646062 | AD42: 102.6498 | AE42: 111.45392 | AF42: 121.13844
R43: =(S43-S$30)/S$30 -> 0.29707495 | S43: =S42+0.25% -> 0.1419 | T43: 45.85678 | U43: 49.33377 | V43: 53.197092 | W43: 57.489671 | X43: 62.259204 | Y43: 67.558686 | Z43: 73.446998 | AA43: 79.989568 | AB43: 86.532137 | AC43: 93.728963 | AD43: 101.64547 | AE43: 110.35363 | AF43: 119.93261
R44: =(S44-S$30)/S$30 -> 0.31992687 | S44: =S43+0.25% -> 0.1444 | T44: 45.472132 | U44: 48.911309 | V44: 52.732617 | W44: 56.978514 | X44: 61.696178 | Y44: 66.938027 | Z44: 72.762303 | AA44: 79.233721 | AB44: 85.705139 | AC44: 92.823699 | AD44: 100.65411 | AE44: 109.26757 | AF44: 118.74238
A45: (4)_DCF_PerpetuityMethod | B45: 2016 | C45: 2017 | D45: 2018 | E45: 2019 | F45: 2020 | G45: Terminal | R45: =(S45-S$30)/S$30 -> 0.34277879 | S45: =S44+0.25% -> 0.1469 | T45: 45.092361 | U45: 48.494218 | V45: 52.274058 | W45: 56.473881 | X45: 61.140351 | Y45: 66.325318 | Z45: 72.086392 | AA45: 78.487585 | AB45: 84.888778 | AC45: 91.930091 | AD45: 99.675535 | AE45: 108.19552 | AF45: 117.56751
AC46: =AVERAGE(AC24:AC38) -> 105.70272
A47: Cash Flow (FCF) | B47: =O10*1000000 -> 1.2919555e+08 | C47: =P10*1000000 -> 1.4857488e+08 | D47: =Q10*1000000 -> 1.6640386e+08 | E47: =R10*1000000 -> 1.8304425e+08 | F47: =S10*1000000 -> 2.0134867e+08 | G47: =B41 -> 2.4218826e+09 | Y47: IR vs. Total Debt
A48: PV(CF) | B48: =B47/(1+$B$33)^1 -> 1.1694021e+08 | C48: =C47/(1+$B$33)^2 -> 1.2172451e+08 | D48: =D47/(1+$B$33)^3 -> 1.2339922e+08 | E48: =E47/(1+$B$33)^4 -> 1.2286309e+08 | F48: =F47/(1+$B$33)^5 -> 1.2232929e+08 | G48: =G47/(1+$B$33)^5 -> 1.4714136e+09
S49: =B68 -> 92.452066 | T49: 0 | U49: =T49+0.5% -> 0.005 | V49: =U49+0.5% -> 0.01 | W49: =V49+0.5% -> 0.015 | X49: =W49+0.5% -> 0.02 | Y49: =X49+0.5% -> 0.025 | Z49: =Y49+0.5% -> 0.03 | AA49: =Z49+0.5% -> 0.035 | AB49: =AA49+0.5% -> 0.04 | ... AF49: =AE49+0.5% -> 0.06
A50: Enterprise Value | B50: =SUM(B48:G48) -> 2.0786699e+09 | S50: 0 | T50: 92.452066 | U50: 92.452066 | V50: 92.452066 | W50: 92.452066 | X50: 92.452066 | Y50: 92.452066 | Z50: 92.452066 | AA50: 92.452066 | AB50: 92.452066 | AC50: 92.452066 | AD50: 92.452066 | AE50: 92.452066 | AF50: 92.452066
A51: -LT debt | B51: =B29 -> 0 | S51: =S50+250000000 -> 250000000 | T51: 93.759297 | U51: 93.710838 | V51: 93.662411 | W51: 93.614019 | X51: 93.56566 | Y51: 93.517334 | Z51: 93.469042 | AA51: 93.420783 | AB51: 93.372557 | AC51: 93.324365 | AD51: 93.276206 | AE51: 93.22808 | AF51: 93.179988
A52: +Cash/eqv | B52: ='ALGN(BS)'!N7*1000000 -> 612966000 | S52: =S51+250000000 -> 500000000 | T52: 95.004528 | U52: 94.909103 | V52: 94.813805 | W52: 94.718636 | X52: 94.623594 | Y52: 94.528679 | Z52: 94.433892 | AA52: 94.339231 | AB52: 94.244698 | AC52: 94.150291 | AD52: 94.05601 | AE52: 93.961856 | AF52: 93.867828
S53: =S52+250000000 -> 750000000 | T53: 96.19195 | U53: 96.051017 | V53: 95.910359 | W53: 95.769975 | X53: 95.629866 | Y53: 95.490031 | Z53: 95.350468 | AA53: 95.211178 | AB53: 95.072159 | AC53: 94.933412 | AD53: 94.794935 | AE53: 94.656728 | AF53: 94.51879
A54: Value of Equity | B54: =B50-B51+B52 -> 2.6916359e+09 | S54: =S53+250000000 -> 1000000000 | T54: 97.325398 | U54: 97.140374 | V54: 96.95582 | W54: 96.771733 | X54: 96.588111 | Y54: 96.404954 | Z54: 96.22226 | AA54: 96.040028 | AB54: 95.858256 | AC54: 95.676943 | AD54: 95.496087 | AE54: 95.315688 | AF54: 95.135744
A55: PRICE PER SHARE VALUATION: | B55: =(B54/B$26) -> 33.701478 | S55: =S54+250000000 -> 1250000000 | T55: 98.408385 | U55: 98.180648 | V55: 97.953612 | W55: 97.727275 | X55: 97.501634 | Y55: 97.276687 | Z55: 97.052431 | AA55: 96.828864 | AB55: 96.605984 | AC55: 96.383787 | AD55: 96.162271 | AE55: 95.941434 | AF55: 95.721274
S56: =S55+250000000 -> 1500000000 | T56: 99.444135 | U56: 99.175016 | V56: 98.906865 | W56: 98.639678 | X56: 98.373451 | Y56: 98.10818 | Z56: 97.843861 | AA56: 97.580489 | AB56: 97.318061 | AC56: 97.056573 | AD56: 96.796021 | AE56: 96.536401 | AF56: 96.277708
S57: =S56+250000000 -> 1750000000 | T57: 100.43561 | U57: 100.1264 | V57: 99.818449 | W57: 99.511757 | X57: 99.206317 | Y57: 98.902123 | Z57: 98.599169 | AA57: 98.297449 | AB57: 97.996957 | AC57: 97.697688 | AD57: 97.399635 | AE57: 97.102792 | AF57: 96.807154
A58: (4)_DCF_GrowthMethod | B58: 2016 | C58: 2017 | D58: 2018 | E58: 2019 | F58: 2020 | G58: Terminal | J58: Modeul_Input | K58: Res_Input | S58: =S57+250000000 -> 2000000000 | T58: 101.38554 | U58: 101.03748 | V58: 100.691 | W58: 100.34609 | X58: 100.00275 | Y58: 99.660977 | Z58: 99.320751 | AA58: 98.982069 | AB58: 98.644921 | AC58: 98.309301 | AD58: 97.975199 | AE58: 97.642608 | AF58: 97.311519 | AG58: =AVERAGE(T58:AD58) -> 99.668734
I59: EV | J59: =B79 -> 6623782870 | K59: =J59 -> 6623782870 | S59: =S58+250000000 -> 2250000000 | T59: 102.29644 | U59: 101.91072 | V59: 101.52692 | W59: 101.14504 | X59: 100.76507 | Y59: 100.38699 | Z59: 100.0108 | AA59: 99.63647 | AB59: 99.264005 | AC59: 98.89339 | AD59: 98.524614 | AE59: 98.157667 | AF59: 97.792537
A60: Cash Flow (FCF) | B60: =B47 -> 1.2919555e+08 | C60: =C47 -> 1.4857488e+08 | D60: =D47 -> 1.6640386e+08 | E60: =E47 -> 1.8304425e+08 | F60: =F47 -> 2.0134867e+08 | G60: =K62 -> 1.0145094e+10 | I60: EBITDA_5 | J60: =(S4+S7)*1000000 -> 3.9019592e+08 | K60: =J60 -> 3.9019592e+08 | L60: 400000000 | S60: =S59+250000000 -> 2500000000 | T60: 103.17062 | U60: 102.74839 | V60: 102.32846 | W60: 101.9108 | X60: 101.49539 | Y60: 101.08223 | Z60: 100.67131 | AA60: 100.26259 | AB60: 99.856083 | AC60: 99.451761 | AD60: 99.049613 | AE60: 98.649626 | AF60: 98.251786
A61: PV(CF) | B61: =B60/(1+$B$33)^1 -> 1.1694021e+08 | C61: =C60/(1+$B$33)^2 -> 1.2172451e+08 | D61: =D60/(1+$B$33)^3 -> 1.2339922e+08 | E61: =E60/(1+$B$33)^4 -> 1.2286309e+08 | F61: =F60/(1+$B$33)^5 -> 1.2232929e+08 | G61: =G60/(1+$B$33)^5 -> 6.1636469e+09 | I61: EV/EBITDA_Mult | J61: =J59/J60 -> 16.975531 | K61: 26 | L61: =K61 -> 26 | S61: =S60+250000000 -> 2750000000 | T61: 104.01022 | U61: 103.55261 | V61: 103.09766 | W61: 102.64535 | X61: 102.19567 | Y61: 101.7486 | Z61: 101.30413 | AA61: 100.86222 | AB61: 100.42287 | AC61: 99.986067 | AD61: 99.551781 | AE61: 99.119999 | AF61: 98.690706
I62: Terminal Value | J62: =J60*J61 -> 6623782870 | K62: =K60*K61 -> 1.0145094e+10 | L62: =L60*L61 -> 10400000000 | S62: =S61+250000000 -> 3000000000 | T62: 104.81723 | U62: 104.3253 | V62: 103.83641 | W62: 103.35056 | X62: 102.86771 | Y62: 102.38784 | Z62: 101.91095 | AA62: 101.43699 | AB62: 100.96596 | AC62: 100.49782 | AD62: 100.03257 | AE62: 99.57017 | AF62: 99.110612
A63: Enterprise Value | B63: =SUM(B61:G61) -> 6.7709032e+09 | I63: Shares_Outstanding | J63: =B26 -> 79867000 | K63: =B26 -> 79867000 | S63: =S62+250000000 -> 3250000000 | T63: 105.59349 | U63: 105.06826 | V63: 104.54647 | W63: 104.02812 | X63: 103.51316 | Y63: 103.00157 | Z63: 102.49332 | AA63: 101.9884 | AB63: 101.48677 | AC63: 100.98842 | AD63: 100.4933 | AE63: 100.00141 | AF63: 99.51271
A64: -LT debt | B64: =B51 -> 0 | I64: Val_PerShare | J64: =J62/J63 -> 82.935166 | K64: =K62/K63 -> 127.02485 | S64: =S63+250000000 -> 3500000000 | T64: 106.34069 | U64: 105.78315 | V64: 105.22947 | W64: 104.67961 | X64: 104.13355 | Y64: 103.59126 | Z64: 103.0527 | AA64: 102.51784 | AB64: 101.98666 | AC64: 101.45913 | AD64: 100.93521 | AE64: 100.41488 | AF64: 99.898106
A65: +Cash/eqv | B65: =B52 -> 612966000 | S65: =S64+250000000 -> 3750000000 | T65: 107.06041 | U65: 106.47152 | V65: 105.88689 | W65: 105.3065 | X65: 104.73031 | Y65: 104.15829 | Z65: 103.5904 | AA65: 103.0266 | AB65: 102.46686 | AC65: 101.91114 | AD65: 101.35942 | AE65: 100.81166 | AF65: 100.26782
S66: =S65+250000000 -> 4000000000 | T66: 107.75414 | U66: 107.1348 | V66: 106.52015 | W66: 105.91015 | X66: 105.30476 | Y66: 104.70394 | Z66: 104.10765 | AA66: 103.51584 | AB66: 102.92849 | AC66: 102.34554 | AD66: 101.76697 | AE66: 101.19272 | AF66: 100.62277
A67: Value of Equity | B67: =B63-B64+B65 -> 7.3838692e+09 | S67: =S66+250000000 -> 4250000000 | T67: 108.42322 | U67: 107.77432 | V67: 107.13053 | W67: 106.4918 | X67: 105.8581 | Y67: 105.22938 | Z67: 104.60559 | AA67: 103.98668 | AB67: 103.37261 | AC67: 102.76333 | AD67: 102.15881 | AE67: 101.559 | AF67: 100.96385
A68: PRICE PER SHARE VALUATION: | B68: =(B67/B$26) -> 92.452066 | S68: =S67+250000000 -> 4500000000 | T68: 109.06895 | U68: 108.39132 | V68: 107.71924 | W68: 107.05264 | X68: 106.39148 | Y68: 105.73571 | Z68: 105.08527 | AA68: 104.44011 | AB68: 103.80019 | AC68: 103.16545 | AD68: 102.53584 | AE68: 101.91131 | AF68: 101.29183
S69: =S68+250000000 -> 4750000000 | T69: 109.69251 | U69: 108.98697 | V69: 108.28741 | W69: 107.59375 | X69: 106.90595 | Y69: 106.22395 | Z69: 105.54768 | AA69: 104.87709 | AB69: 104.21213 | AC69: 103.55275 | AD69: 102.89887 | AE69: 102.25046 | AF69: 101.60746
S70: =S69+250000000 -> 5000000000 | T70: 110.29501 | U70: 109.56235 | V70: 108.83608 | W70: 108.11615 | X70: 107.40249 | Y70: 106.69504 | Z70: 105.99373 | AA70: 105.2985 | AB70: 104.60929 | AC70: 103.92603 | AD70: 103.24868 | AE70: 102.57716 | AF70: 101.91142
J71: D/S | K71: =B30/B26 -> 0 | S71: =S70+250000000 -> 5250000000 | T71: 110.8775 | U71: 110.11845 | V71: 109.36624 | W71: 108.62078 | X71: 107.88202 | Y71: 107.14986 | Z71: 106.42426 | AA71: 105.70513 | AB71: 104.99242 | AC71: 104.28605 | AD71: 103.58596 | AE71: 102.89207 | AF71: 102.20434
J72: FCF/Share | K72: =B63/B26 -> 84.777232 | S72: =S71+250000000 -> 5500000000 | T72: 111.44093 | U72: 110.65624 | V72: 109.8788 | W72: 109.10854 | X72: 108.34538 | Y72: 107.58925 | Z72: 106.84007 | AA72: 106.09777 | AB72: 105.36226 | AC72: 104.63349 | AD72: 103.91137 | AE72: 103.19584 | AF72: 102.48682
S73: =S72+250000000 -> 5750000000 | T73: 111.98624 | U73: 111.17658 | V73: 110.37461 | W73: 109.58024 | X73: 108.79338 | Y73: 108.01397 | Z73: 107.2419 | AA73: 106.4771 | AB73: 105.71949 | AC73: 104.969 | AD73: 104.22554 | AE73: 103.48903 | AF73: 102.7594
S74: =S73+250000000 -> 6000000000 | T74: 112.51426 | U74: 111.68031 | V74: 110.85447 | W74: 110.03666 | X74: 109.22677 | Y74: 108.42473 | Z74: 107.63043 | AA74: 106.8438 | AB74: 106.06475 | AC74: 105.29318 | AD74: 104.52902 | AE74: 103.77219 | AF74: 103.02259
T75: =AVERAGE(T51:T58) -> 97.744356
A76: **EQUITY MULTIPLE METHOD
A77: Final Year (2020) EBITDA | B77: =S4*1000000 -> 3.5988944e+08 | AC77: min | AD77: =MIN(T50:AD58) -> 92.452066
A78: 2015_EBITDA | B78: =N4*1000000 -> 188634000 | AC78: max | AD78: =MAX(T50:AD58) -> 101.38554
A79: EV | B79: =(B31+B30-B52) -> 6623782870 | AC79: avg | AD79: =AVERAGE(T50:AD58) -> 96.263076
B80: (Calculated) | C80: -5 | D80: -4 | E80: -3 | F80: -2 | G80: -1 | H80: 1 | I80: 2 | J80: 3 | K80: 4 | L80: 5
A81: EBITDA_Mult | B81: =B79/B78 -> 35.11447 | C81: =$B$81+C80 -> 30.11447 | D81: =$B$81+D80 -> 31.11447 | E81: =$B$81+E80 -> 32.11447 | F81: =$B$81+F80 -> 33.11447 | G81: =$B$81+G80 -> 34.11447 | H81: =$B$81+H80 -> 36.11447 | I81: =$B$81+I80 -> 37.11447 | J81: =$B$81+J80 -> 38.11447 | ... L81: =$B$81+L80 -> 40.11447
A82: Final_Year_Val (EV) | B82: =$B$77*B81 -> 1.2637327e+10 | C82: =$B$77*C81 -> 1.083788e+10 | D82: =$B$77*D81 -> 1.1197769e+10 | E82: =$B$77*E81 -> 1.1557659e+10 | F82: =$B$77*F81 -> 1.1917548e+10 | G82: =$B$77*G81 -> 1.2277438e+10 | H82: =$B$77*H81 -> 1.2997216e+10 | I82: =$B$77*I81 -> 1.3357106e+10 | ... L82: =$B$77*L81 -> 1.4436774e+10
A83: -LT debt | B83: =B51 -> 0
A84: +cash/eqv | B84: =B52 -> 612966000
A85: Equity Value | B85: =B82-$B$83+$B$84 -> 1.3250293e+10 | C85: =C82-$B$83+$B$84 -> 1.1450846e+10 | D85: =D82-$B$83+$B$84 -> 1.1810735e+10 | E85: =E82-$B$83+$B$84 -> 1.2170625e+10 | F85: =F82-$B$83+$B$84 -> 1.2530514e+10 | G85: =G82-$B$83+$B$84 -> 1.2890404e+10 | H85: =H82-$B$83+$B$84 -> 1.3610182e+10 | I85: =I82-$B$83+$B$84 -> 1.3970072e+10 | ... L85: =L82-$B$83+$B$84 -> 1.504974e+10
A86: Shares_Outstanding | B86: =B26 -> 79867000
A87: Val_PerShare | B87: =B85/$B$86 -> 165.90448 | C87: =C85/$B$86 -> 143.37393 | D87: =D85/$B$86 -> 147.88004 | E87: =E85/$B$86 -> 152.38615 | F87: =F85/$B$86 -> 156.89226 | G87: =G85/$B$86 -> 161.39837 | H87: =H85/$B$86 -> 170.41059 | I87: =I85/$B$86 -> 174.9167 | ... L87: =L85/$B$86 -> 188.43503
G88: =AVERAGE(F87:I87) -> 165.90448

Sheet Credit
A1: CA | F1: ='ALGN(BS_Annual)'!C22 -> 184.517 | G1: ='ALGN(BS_Annual)'!D22 -> 177.907 | H1: ='ALGN(BS_Annual)'!E22 -> 261.299 | I1: ='ALGN(BS_Annual)'!F22 -> 388.611 | J1: ='ALGN(BS_Annual)'!G22 -> 384.816 | K1: ='ALGN(BS_Annual)'!H22 -> 485.793 | L1: ='ALGN(BS_Annual)'!I22 -> 544.676 | M1: ='ALGN(BS_Annual)'!J22 -> 657.16 | N1: ='ALGN(BS_Annual)'!K22 -> 732.01
A2: TA | F2: ='ALGN(BS_Annual)'!C36 -> 222.761 | G2: ='ALGN(BS_Annual)'!D36 -> 279.341 | H2: ='ALGN(BS_Annual)'!E36 -> 355.24 | I2: ='ALGN(BS_Annual)'!F36 -> 476.943 | J2: ='ALGN(BS_Annual)'!G36 -> 649.264 | K2: ='ALGN(BS_Annual)'!H36 -> 756.312 | L2: ='ALGN(BS_Annual)'!I36 -> 832.147 | M2: ='ALGN(BS_Annual)'!J36 -> 987.997 | N2: ='ALGN(BS_Annual)'!K36 -> 1158.633
A3: CL | F3: ='ALGN(BS_Annual)'!C51 -> 61.459 | G3: ='ALGN(BS_Annual)'!D51 -> 60.572 | H3: ='ALGN(BS_Annual)'!E51 -> 81.243 | I3: ='ALGN(BS_Annual)'!F51 -> 92.974 | J3: ='ALGN(BS_Annual)'!G51 -> 148.117 | K3: ='ALGN(BS_Annual)'!H51 -> 155.771 | L3: ='ALGN(BS_Annual)'!I51 -> 175.338 | M3: ='ALGN(BS_Annual)'!J51 -> 201.811 | N3: ='ALGN(BS_Annual)'!K51 -> 271.672
A4: TL | F4: ='ALGN(BS_Annual)'!C64 -> 61.607 | G4: ='ALGN(BS_Annual)'!D64 -> 60.801 | H4: ='ALGN(BS_Annual)'!E64 -> 82.204 | I4: ='ALGN(BS_Annual)'!F64 -> 99.196 | J4: ='ALGN(BS_Annual)'!G64 -> 158.483 | K4: ='ALGN(BS_Annual)'!H64 -> 174.995 | L4: ='ALGN(BS_Annual)'!I64 -> 198.177 | M4: ='ALGN(BS_Annual)'!J64 -> 235.226 | N4: ='ALGN(BS_Annual)'!K64 -> 310.707
A5: SO | F5: ='ALGN(BS_Annual)'!C79 -> 68.642 | G5: ='ALGN(BS_Annual)'!D79 -> 65.633 | H5: ='ALGN(BS_Annual)'!E79 -> 74.568 | I5: ='ALGN(BS_Annual)'!F79 -> 76.39 | J5: ='ALGN(BS_Annual)'!G79 -> 78.776 | K5: ='ALGN(BS_Annual)'!H79 -> 80.611 | L5: ='ALGN(BS_Annual)'!I79 -> 80.583 | M5: ='ALGN(BS_Annual)'!J79 -> 80.205 | N5: ='ALGN(BS_Annual)'!K79 -> 79.5
A6: Current Market Cap | F6: 1144.9486 | G6: 574.28875 | H6: 1328.8018 | I6: 1492.6606 | J6: 1868.9606 | K6: 2236.9552 | L6: 4604.5126 | M6: 4484.2616 | N6: 5235.075
A7: Sales (Rev) | F7: ='ALGN(IS)'!C6 -> 284.332 | G7: ='ALGN(IS)'!D6 -> 303.976 | H7: ='ALGN(IS)'!E6 -> 312.333 | I7: ='ALGN(IS)'!F6 -> 387.126 | J7: ='ALGN(IS)'!G6 -> 479.741 | K7: ='ALGN(IS)'!H6 -> 560.041 | L7: ='ALGN(IS)'!I6 -> 660.206 | M7: ='ALGN(IS)'!J6 -> 761.653 | N7: ='ALGN(IS)'!K6 -> 845.486
A8: RE | F8: ='ALGN(BS_Annual)'!C70 -> -289.65 | G8: ='ALGN(BS_Annual)'!D70 -> -221.23 | H8: ='ALGN(BS_Annual)'!E70 -> -252.499 | I8: ='ALGN(BS_Annual)'!F70 -> -178.246 | J8: ='ALGN(BS_Annual)'!G70 -> -116.513 | K8: ='ALGN(BS_Annual)'!H70 -> -89.626 | L8: ='ALGN(BS_Annual)'!I70 -> -95.91 | M8: ='ALGN(BS_Annual)'!J70 -> -30.507 | N8: ='ALGN(BS_Annual)'!K70 -> 27.391
A9: EBIT | F9: ='ALGN(IS)'!C25 -> 32.059 | G9: ='ALGN(IS)'!D25 -> 21.745 | H9: ='ALGN(IS)'!E25 -> 36.98 | I9: ='ALGN(IS)'!F25 -> 98.617 | J9: ='ALGN(IS)'!G25 -> 101.472 | K9: ='ALGN(IS)'!H25 -> 124.234 | L9: ='ALGN(IS)'!I25 -> 161.225 | M9: ='ALGN(IS)'!J25 -> 193.576 | N9: ='ALGN(IS)'!K25 -> 188.634
A10: D/A | F10: ='ALGN(CF)'!C8 -> 13.385 | G10: ='ALGN(CF)'!D8 -> 12.791 | H10: ='ALGN(CF)'!E8 -> 13.004 | I10: ='ALGN(CF)'!F8 -> 14.186 | J10: ='ALGN(CF)'!G8 -> 17.477 | K10: ='ALGN(CF)'!H8 -> 17.811 | L10: ='ALGN(CF)'!I8 -> 16.825 | M10: ='ALGN(CF)'!J8 -> 17.856 | N10: ='ALGN(CF)'!K8 -> 18.004
A11: EBITDA | F11: ='ALGN(IS)'!C12 -> 209.297 | G11: ='ALGN(IS)'!D12 -> 225.126 | H11: ='ALGN(IS)'!E12 -> 233.492 | I11: ='ALGN(IS)'!F12 -> 303.417 | J11: ='ALGN(IS)'!G12 -> 362.435 | K11: ='ALGN(IS)'!H12 -> 417.123 | L11: ='ALGN(IS)'!I12 -> 498.106 | M11: ='ALGN(IS)'!J12 -> 578.443 | N11: ='ALGN(IS)'!K12 -> 640.11
A12: NI | F12: ='ALGN(IS)'!C55 -> 35.724 | G12: ='ALGN(IS)'!D55 -> 79.987 | H12: ='ALGN(IS)'!E55 -> -31.269 | I12: ='ALGN(IS)'!F55 -> 74.253 | J12: ='ALGN(IS)'!G55 -> 66.716 | K12: ='ALGN(IS)'!H55 -> 58.691 | L12: ='ALGN(IS)'!I55 -> 64.295 | M12: ='ALGN(IS)'!J55 -> 145.832 | N12: ='ALGN(IS)'!K55 -> 144.02
A13: CFO | F13: ='ALGN(CF)'!C21 -> 52.777 | G13: ='ALGN(CF)'!D21 -> 39.746 | H13: ='ALGN(CF)'!E21 -> 74.165 | I13: ='ALGN(CF)'!F21 -> 129.529 | J13: ='ALGN(CF)'!G21 -> 130.469 | K13: ='ALGN(CF)'!H21 -> 133.778 | L13: ='ALGN(CF)'!I21 -> 185.976 | M13: ='ALGN(CF)'!J21 -> 226.899 | N13: ='ALGN(CF)'!K21 -> 237.997
A14: WC | F14: =F2-F4 -> 161.154 | G14: =G2-G4 -> 218.54 | H14: =H2-H4 -> 273.036 | I14: =I2-I4 -> 377.747 | J14: =J2-J4 -> 490.781 | K14: =K2-K4 -> 581.317 | L14: =L2-L4 -> 633.97 | M14: =M2-M4 -> 752.771 | N14: =N2-N4 -> 847.926
A16: (Z-Score Model) | C16: 2004 | D16: 2005 | E16: 2006 | F16: 2007 | G16: 2008 | H16: 2009 | I16: 2010 | J16: 2011 | K16: 2012 | L16: 2013 | M16: 2014 | N16: 2015
A17: Total Assets (TA) | F17: =F2 -> 222.761 | G17: =G2 -> 279.341 | H17: =H2 -> 355.24 | I17: =I2 -> 476.943 | J17: =J2 -> 649.264 | K17: =K2 -> 756.312 | L17: =L2 -> 832.147 | M17: =M2 -> 987.997 | N17: =N2 -> 1158.633
A18: Working Capital | F18: =F14 -> 161.154 | G18: =G14 -> 218.54 | H18: =H14 -> 273.036 | I18: =I14 -> 377.747 | J18: =J14 -> 490.781 | K18: =K14 -> 581.317 | L18: =L14 -> 633.97 | M18: =M14 -> 752.771 | N18: =N14 -> 847.926
A19: WC/TA | F19: =F18/F$17 -> 0.72343902 | G19: =G18/G$17 -> 0.7823413 | H19: =H18/H$17 -> 0.76859588 | I19: =I18/I$17 -> 0.79201708 | J19: =J18/J$17 -> 0.75590361 | K19: =K18/K$17 -> 0.76862062 | L19: =L18/L$17 -> 0.76184857 | M19: =M18/M$17 -> 0.76191628 | N19: =N18/N$17 -> 0.73183312
A20: Retained Earnings | F20: =F8 -> -289.65 | G20: =G8 -> -221.23 | H20: =H8 -> -252.499 | I20: =I8 -> -178.246 | J20: =J8 -> -116.513 | K20: =K8 -> -89.626 | L20: =L8 -> -95.91 | M20: =M8 -> -30.507 | N20: =N8 -> 27.391
A21: RE/TA | F21: =F20/F$17 -> -1.3002725 | G21: =G20/G$17 -> -0.7919711 | H21: =H20/H$17 -> -0.71078426 | I21: =I20/I$17 -> -0.373726 | J21: =J20/J$17 -> -0.17945397 | K21: =K20/K$17 -> -0.118504 | L21: =L20/L$17 -> -0.11525608 | M21: =M20/M$17 -> -0.030877624 | N21: =N20/N$17 -> 0.02364079
A22: EBIT | F22: =F9 -> 32.059 | G22: =G9 -> 21.745 | H22: =H9 -> 36.98 | I22: =I9 -> 98.617 | J22: =J9 -> 101.472 | K22: =K9 -> 124.234 | L22: =L9 -> 161.225 | M22: =M9 -> 193.576 | N22: =N9 -> 188.634
A23: EBIT/TA | F23: =F22/F$17 -> 0.14391657 | G23: =G22/G$17 -> 0.077843926 | H23: =H22/H$17 -> 0.10409864 | I23: =I22/I$17 -> 0.20676894 | J23: =J22/J$17 -> 0.15628774 | K23: =K22/K$17 -> 0.1642629 | L23: =L22/L$17 -> 0.19374582 | M23: =M22/M$17 -> 0.19592772 | N23: =N22/N$17 -> 0.16280738
A24: EBITDA | F24: =F11 -> 209.297 | G24: =G11 -> 225.126 | H24: =H11 -> 233.492 | I24: =I11 -> 303.417 | J24: =J11 -> 362.435 | K24: =K11 -> 417.123 | L24: =L11 -> 498.106 | M24: =M11 -> 578.443 | N24: =N11 -> 640.11
A25: EBITDA/TA | F25: =F24/F$17 -> 0.93955854 | G25: =G24/G$17 -> 0.80591821 | H25: =H24/H$17 -> 0.65727959 | I25: =I24/I$17 -> 0.63617036 | J25: =J24/J$17 -> 0.55822439 | K25: =K24/K$17 -> 0.55152239 | L25: =L24/L$17 -> 0.59857934 | M25: =M24/M$17 -> 0.5854704 | N25: =N24/N$17 -> 0.55247002
A26: Shares Outstanding | F26: =F5 -> 68.642 | G26: =G5 -> 65.633 | H26: =H5 -> 74.568 | I26: =I5 -> 76.39 | J26: =J5 -> 78.776 | K26: =K5 -> 80.611 | L26: =L5 -> 80.583 | M26: =M5 -> 80.205 | N26: =N5 -> 79.5
A27: MV_Equity | F27: =F6 -> 1144.9486 | G27: =G6 -> 574.28875 | H27: =H6 -> 1328.8018 | I27: =I6 -> 1492.6606 | J27: =J6 -> 1868.9606 | K27: =K6 -> 2236.9552 | L27: =L6 -> 4604.5126 | M27: =M6 -> 4484.2616 | N27: =N6 -> 5235.075
A28: BV_TL | F28: =F4 -> 61.607 | G28: =G4 -> 60.801 | H28: =H4 -> 82.204 | I28: =I4 -> 99.196 | J28: =J4 -> 158.483 | K28: =K4 -> 174.995 | L28: =L4 -> 198.177 | M28: =M4 -> 235.226 | N28: =N4 -> 310.707
A29: MV_E/BV_TL | F29: =F27/F28 -> 18.584715 | G29: =G27/G28 -> 9.4453833 | H29: =H27/H28 -> 16.164685 | I29: =I27/I28 -> 15.047589 | J29: =J27/J28 -> 11.792814 | K29: =K27/K28 -> 12.782967 | L29: =L27/L28 -> 23.234344 | M29: =M27/M28 -> 19.063631 | N29: =N27/N28 -> 16.848912
A30: Sales | F30: =F7 -> 284.332 | G30: =G7 -> 303.976 | H30: =H7 -> 312.333 | I30: =I7 -> 387.126 | J30: =J7 -> 479.741 | K30: =K7 -> 560.041 | L30: =L7 -> 660.206 | M30: =M7 -> 761.653 | N30: =N7 -> 845.486
A31: Sales/TA | F31: =F30/F$17 -> 1.2763994 | G31: =G30/G$17 -> 1.0881897 | H31: =H30/H$17 -> 0.87921687 | I31: =I30/I$17 -> 0.8116819 | J31: =J30/J$17 -> 0.73889974 | K31: =K30/K$17 -> 0.74048937 | L31: =L30/L$17 -> 0.79337665 | M31: =M30/M$17 -> 0.77090619 | N31: =N30/N$17 -> 0.72972719
A33: x1 | E33: 1.2 | F33: =F19*$E$33 -> 0.86812683 | G33: =G19*$E$33 -> 0.93880956 | H33: =H19*$E$33 -> 0.92231505 | I33: =I19*$E$33 -> 0.95042049 | J33: =J19*$E$33 -> 0.90708433 | K33: =K19*$E$33 -> 0.92234475 | L33: =L19*$E$33 -> 0.91421828 | M33: =M19*$E$33 -> 0.91429954 | N33: =N19*$E$33 -> 0.87819974
A34: x2 | E34: 1.4 | F34: =$E$34*F21 -> -1.8203815 | G34: =$E$34*G21 -> -1.1087595 | H34: =$E$34*H21 -> -0.99509796 | I34: =$E$34*I21 -> -0.5232164 | J34: =$E$34*J21 -> -0.25123555 | K34: =$E$34*K21 -> -0.16590561 | L34: =$E$34*L21 -> -0.16135851 | M34: =$E$34*M21 -> -0.043228674 | N34: =$E$34*N21 -> 0.033097107
A35: x3 | E35: 3.3 | F35: =$E$35*F23 -> 0.4749247 | G35: =$E$35*G23 -> 0.25688495 | H35: =$E$35*H23 -> 0.3435255 | I35: =$E$35*I23 -> 0.68233751 | J35: =$E$35*J23 -> 0.51574953 | K35: =$E$35*K23 -> 0.54206756 | L35: =$E$35*L23 -> 0.63936119 | M35: =$E$35*M23 -> 0.64656148 | N35: =$E$35*N23 -> 0.53726435
A36: x4 | E36: 0.6 | F36: =$E$36*F29 -> 11.150829 | G36: =$E$36*G29 -> 5.66723 | H36: =$E$36*H29 -> 9.698811 | I36: =$E$36*I29 -> 9.0285532 | J36: =$E$36*J29 -> 7.0756886 | K36: =$E$36*K29 -> 7.66978 | L36: =$E$36*L29 -> 13.940606 | M36: =$E$36*M29 -> 11.438178 | N36: =$E$36*N29 -> 10.109347
A37: x5 | E37: 0.99 | F37: =$E$37*F31 -> 1.2636354 | G37: =$E$37*G31 -> 1.0773078 | H37: =$E$37*H31 -> 0.8704247 | I37: =$E$37*I31 -> 0.80356508 | J37: =$E$37*J31 -> 0.73151074 | K37: =$E$37*K31 -> 0.73308448 | L37: =$E$37*L31 -> 0.78544288 | M37: =$E$37*M31 -> 0.76319713 | N37: =$E$37*N31 -> 0.72242992
A39: Z-Score: | F39: =SUM(F33:F37) -> 11.937135 | G39: =SUM(G33:G37) -> 6.8314728 | H39: =SUM(H33:H37) -> 10.839978 | I39: =SUM(I33:I37) -> 10.94166 | J39: =SUM(J33:J37) -> 8.9787977 | K39: =SUM(K33:K37) -> 9.7013712 | L39: =SUM(L33:L37) -> 16.11827 | M39: =SUM(M33:M37) -> 13.719008 | N39: =SUM(N33:N37) -> 12.280338
A40: z < 1.8 = bad
A41: z > 3 = really good
A42: 1.8 < z < 3.0 = safe
A44: (O-Score Model) | B44: 2003 | C44: 2004 | D44: 2005 | E44: 2006 | F44: 2007 | G44: 2008 | H44: 2009 | I44: 2010 | J44: 2011 | K44: 2012 | L44: 2013 | M44: 2014 | N44: 2015
A46: TA | F46: =F2 -> 222.761 | G46: =G2 -> 279.341 | H46: =H2 -> 355.24 | I46: =I2 -> 476.943 | J46: =J2 -> 649.264 | K46: =K2 -> 756.312 | L46: =L2 -> 832.147 | M46: =M2 -> 987.997 | N46: =N2 -> 1158.633
A47: TL | F47: =F4 -> 61.607 | G47: =G4 -> 60.801 | H47: =H4 -> 82.204 | I47: =I4 -> 99.196 | J47: =J4 -> 158.483 | K47: =K4 -> 174.995 | L47: =L4 -> 198.177 | M47: =M4 -> 235.226 | N47: =N4 -> 310.707
A48: WC | F48: =F14 -> 161.154 | G48: =G14 -> 218.54 | H48: =H14 -> 273.036 | I48: =I14 -> 377.747 | J48: =J14 -> 490.781 | K48: =K14 -> 581.317 | L48: =L14 -> 633.97 | M48: =M14 -> 752.771 | N48: =N14 -> 847.926
A49: CL | F49: =F3 -> 61.459 | G49: =G3 -> 60.572 | H49: =H3 -> 81.243 | I49: =I3 -> 92.974 | J49: =J3 -> 148.117 | K49: =K3 -> 155.771 | L49: =L3 -> 175.338 | M49: =M3 -> 201.811 | N49: =N3 -> 271.672
A50: CA | F50: =F1 -> 184.517 | G50: =G1 -> 177.907 | H50: =H1 -> 261.299 | I50: =I1 -> 388.611 | J50: =J1 -> 384.816 | K50: =K1 -> 485.793 | L50: =L1 -> 544.676 | M50: =M1 -> 657.16 | N50: =N1 -> 732.01
A51: X, 1 if TL > TA, else 0 | F51: 0 | G51: 0 | H51: 0 | I51: 0 | J51: 0 | K51: 0 | L51: 0 | M51: 0 | N51: 0
A52: NI | F52: =F12 -> 35.724 | G52: =G12 -> 79.987 | H52: =H12 -> -31.269 | I52: =I12 -> 74.253 | J52: =J12 -> 66.716 | K52: =K12 -> 58.691 | L52: =L12 -> 64.295 | M52: =M12 -> 145.832 | N52: =N12 -> 144.02
A53: CFO | F53: =F13 -> 52.777 | G53: =G13 -> 39.746 | H53: =H13 -> 74.165 | I53: =I13 -> 129.529 | J53: =J13 -> 130.469 | K53: =K13 -> 133.778 | L53: =L13 -> 185.976 | M53: =M13 -> 226.899 | N53: =N13 -> 237.997
A54: Y, 1 if net loss for last 2 years, else 0 | F54: 0 | G54: 0 | H54: 0 | I54: 0 | J54: 0 | K54: 0 | L54: 0 | M54: 0 | N54: 0
A55: GNP_IndexLevel.Close | F55: ='FRED Graph'!I20 -> 360 | G55: ='FRED Graph'!J20 -> 380.5 | H55: ='FRED Graph'!K20 -> 378.8 | I55: ='FRED Graph'!L20 -> 392.1 | J55: ='FRED Graph'!M20 -> 404.1 | K55: ='FRED Graph'!N20 -> 413.5 | L55: ='FRED Graph'!O20 -> 427.7 | M55: ='FRED Graph'!P20 -> 439.6 | N55: ='FRED Graph'!Q20 -> 459.3
A57: Weights:
A59: -1.32 | F59: =$A59 -> -1.32 | G59: =$A59 -> -1.32 | H59: =$A59 -> -1.32 | I59: =$A59 -> -1.32 | J59: =$A59 -> -1.32 | K59: =$A59 -> -1.32 | L59: =$A59 -> -1.32 | M59: =$A59 -> -1.32 | N59: =$A59 -> -1.32
A60: x1 | F60: =-0.407*LOG(F46/F55) -> 0.08484458 | G60: =-0.407*LOG(G46/G55) -> 0.054627531 | H60: =-0.407*LOG(H46/H55) -> 0.01135046 | I60: =-0.407*LOG(I46/I55) -> -0.034623342 | J60: =-0.407*LOG(J46/J55) -> -0.083814516 | K60: =-0.407*LOG(K46/K55) -> -0.10672577 | L60: =-0.407*LOG(L46/L55) -> -0.11764775 | M60: =-0.407*LOG(M46/M55) -> -0.14314106 | N60: =-0.407*LOG(N46/N55) -> -0.16355273
A61: x2 | F61: =6.03*(F47/F46) -> 1.6676627 | G61: =6.03*(G47/G46) -> 1.312482 | H61: =6.03*(H47/H46) -> 1.3953669 | I61: =6.03*(I47/I46) -> 1.254137 | J61: =6.03*(J47/J46) -> 1.4719012 | K61: =6.03*(K47/K46) -> 1.3952176 | L61: =6.03*(L47/L46) -> 1.4360531 | M61: =6.03*(M47/M46) -> 1.4356448 | N61: =6.03*(N47/N46) -> 1.6170463
A62: x3 | F62: =-1.43*(F48/F46) -> -1.0345178 | G62: =-1.43*(G48/G46) -> -1.1187481 | H62: =-1.43*(H48/H46) -> -1.0990921 | I62: =-1.43*(I48/I46) -> -1.1325844 | J62: =-1.43*(J48/J46) -> -1.0809422 | K62: =-1.43*(K48/K46) -> -1.0991275 | L62: =-1.43*(L48/L46) -> -1.0894435 | M62: =-1.43*(M48/M46) -> -1.0895403 | N62: =-1.43*(N48/N46) -> -1.0465214
A63: x4 | F63: =0.0757*((F49-F50)/F46) -> -0.041818319 | G63: =0.0757*((G49-G50)/G46) -> -0.031797192 | H63: =0.0757*((H49-H50)/H46) -> -0.0383691 | I63: =0.0757*((I49-I50)/I46) -> -0.046923261 | J63: =0.0757*((J49-J50)/J46) -> -0.027597579 | K63: =0.0757*((K49-K50)/K46) -> -0.033032221 | L63: =0.0757*((L49-L50)/L46) -> -0.033598495 | M63: =0.0757*((M49-M50)/M46) -> -0.034888688 | N63: =0.0757*((N49-N50)/N46) -> -0.030076466
A64: x5 | F64: =-1.72*F51 -> 0 | G64: =-1.72*G51 -> 0 | H64: =-1.72*H51 -> 0 | I64: =-1.72*I51 -> 0 | J64: =-1.72*J51 -> 0 | K64: =-1.72*K51 -> 0 | L64: =-1.72*L51 -> 0 | M64: =-1.72*M51 -> 0 | N64: =-1.72*N51 -> 0
A65: x6 | F65: =-2.37*(F52/F46) -> -0.38007497 | G65: =-2.37*(G52/G46) -> -0.67863003 | H65: =-2.37*(H52/H46) -> 0.20861257 | I65: =-2.37*(I52/I46) -> -0.36897409 | J65: =-2.37*(J52/J46) -> -0.24353255 | K65: =-2.37*(K52/K46) -> -0.18391573 | L65: =-2.37*(L52/L46) -> -0.18311566 | M65: =-2.37*(M52/M46) -> -0.34982074 | N65: =-2.37*(N52/N46) -> -0.29459492
A66: x7 | F66: =-1.83*(F53/F47) -> -1.56771 | G66: =-1.83*(G53/G47) -> -1.1962826 | H66: =-1.83*(H53/H47) -> -1.6510383 | I66: =-1.83*(I53/I47) -> -2.389593 | J66: =-1.83*(J53/J47) -> -1.5065229 | K66: =-1.83*(K53/K47) -> -1.3989756 | L66: =-1.83*(L53/L47) -> -1.7173339 | M66: =-1.83*(M53/M47) -> -1.765218 | N66: =-1.83*(N53/N47) -> -1.4017531
A67: x8 | F67: =0.285*F54 -> 0 | G67: =0.285*G54 -> 0 | H67: =0.285*H54 -> 0 | I67: =0.285*I54 -> 0 | J67: =0.285*J54 -> 0 | K67: =0.285*K54 -> 0 | L67: =0.285*L54 -> 0 | M67: =0.285*M54 -> 0 | N67: =0.285*N54 -> 0
A68: x9 | F68: =-0.521*((F52-E52)/(ABS(F52)+ABS(E52))) -> -0.521 | G68: =-0.521*((G52-F52)/(ABS(G52)+ABS(F52))) -> -0.19929845 | H68: =-0.521*((H52-G52)/(ABS(H52)+ABS(G52))) -> 0.521 | I68: =-0.521*((I52-H52)/(ABS(I52)+ABS(H52))) -> -0.521 | J68: =-0.521*((J52-I52)/(ABS(J52)+ABS(I52))) -> 0.027855607 | K68: =-0.521*((K52-J52)/(ABS(K52)+ABS(J52))) -> 0.033339646 | L68: =-0.521*((L52-K52)/(ABS(L52)+ABS(K52))) -> -0.02373997 | M68: =-0.521*((M52-L52)/(ABS(M52)+ABS(L52))) -> -0.20216715 | N68: =-0.521*((N52-M52)/(ABS(N52)+ABS(M52))) -> 0.0032570139
A70: T = | F70: =SUM(F59:F68) -> -3.1126138 | G70: =SUM(G59:G68) -> -3.1776468 | H70: =SUM(H59:H68) -> -1.9721696 | I70: =SUM(I59:I68) -> -4.5595611 | J70: =SUM(J59:J68) -> -2.7626529 | K70: =SUM(K59:K68) -> -2.7132195 | L70: =SUM(L59:L68) -> -3.0488261 | M70: =SUM(M59:M68) -> -3.4691311 | N70: =SUM(N59:N68) -> -2.6361953
A72: E^(T) / (1+E^(T)) | F72: =EXP(F70)/(1+EXP(F70)) -> 0.042589936 | G72: =EXP(G70)/(1+EXP(G70)) -> 0.040015632 | H72: =EXP(H70)/(1+EXP(H70)) -> 0.12215604 | I72: =EXP(I70)/(1+EXP(I70)) -> 0.010358236 | J72: =EXP(J70)/(1+EXP(J70)) -> 0.059376029 | K72: =EXP(K70)/(1+EXP(K70)) -> 0.062197793 | L72: =EXP(L70)/(1+EXP(L70)) -> 0.045268182 | M72: =EXP(M70)/(1+EXP(M70)) -> 0.030203422 | N72: =EXP(N70)/(1+EXP(N70)) -> 0.06684497
A74: * > 0.5 = high chance of defualt
B84: 2015
A85: Invisalign Full | B85: 0.78
A86: Invisalign Express | B86: 0.11
A87: Invisalign Non-Case | B87: 0.06
A88: Scanners and Services | B88: 0.05

Sheet FRED Graph
A1: FRED Graph Observations
A2: Federal Reserve Economic Data
A3: Link: https://fred.stlouisfed.org
A4: Help: https://fred.stlouisfed.org/help-faq
A5: Economic Research Division
A6: Federal Reserve Bank of St. Louis
A8: Y694RC1A027NBEA | B8: Gross Domestic Product: Research and Development, Billions of Dollars, Annual, Not Seasonally Adjusted
A10: Frequency: Annual
A11: observation_date | B11: Y694RC1A027NBEA
A12: 42005 | B12: 459.3 | C12: =B13 -> 439.6 | D12: =B14 -> 427.7 | E12: =B15 -> 413.5 | F12: =B16 -> 404.1 | G12: =B17 -> 392.1 | H12: =B18 -> 374.8 | I12: =B19 -> 380.5 | J12: =B20 -> 360 | K12: =B21 -> 334.6 | L12: =B22 -> 313.1 | M12: =B23 -> 291.2
A13: 41640 | B13: 439.6
A14: 41275 | B14: 427.7
A15: 40909 | B15: 413.5
A16: 40544 | B16: 404.1
A17: 40179 | B17: 392.1 | F17: 459.3 | G17: 439.6 | H17: 427.7 | I17: 413.5 | J17: 404.1 | K17: 392.1 | L17: 374.8 | M17: 380.5 | N17: 360 | O17: 334.6 | P17: 313.1 | Q17: 291.2
A18: 39814 | B18: 374.8 | F18: 2015 | G18: 2014 | H18: 2013 | I18: 2012 | J18: 2011 | K18: 2010 | L18: 2009 | M18: 2008 | N18: 2007 | O18: 2006 | P18: 2005 | Q18: 2004
A19: 39448 | B19: 380.5
A20: 39083 | B20: 360 | F20: 291.2 | G20: 313.1 | H20: 334.6 | I20: 360 | J20: 380.5 | K20: 378.8 | L20: 392.1 | M20: 404.1 | N20: 413.5 | O20: 427.7 | P20: 439.6 | Q20: 459.3
A21: 38718 | B21: 334.6
A22: 38353 | B22: 313.1
A23: 37987 | B23: 291.2
A24: 37622 | B24: 277.6
A25: 37257 | B25: 265.7
A26: 36892 | B26: 263.2
A27: 36526 | B27: 255.6
A28: 36161 | B28: 237.2
A29: 35796 | B29: 222.4
A30: 35431 | B30: 212
A31: 35065 | B31: 199.8
A32: 34700 | B32: 187.5
... A98: 10594 | B98: 0.3

Sheet gg
A1: EQY_FUND_CRNCY | B1: REL_INDEX | C1: FA_ADJUSTED
A2: USD | C2: ADJUSTED
A3: Ticker | B3: Name | C3: Tkr & Exch | D3: Mkt Cap (USD) | E3: Price:D-1 | F3: Curr Shares Out | G3: Tot Debt:Q | H3: C&CE:Q | I3: EBITDA:Q | J3: EBITDA:Y | K3: Beta:Y-1 | L3: Beta:Y-5 | M3: Beta:Y-2 | N3: Avg | O3: Reg Csh DPS | P3: Dvd P/O:Q | Q3: Dvd P/O:Y | R3: Retntn Rt:Q | S3: Retntn Rt:Y
A4: None (11 securities)
A5: Average | B5: Average | D5: 5289.5446 | E5: 110.67818 | F5: 88.145305 | G5: 895.00818 | H5: 292.73755 | I5: 101.65018 | J5: 357.63597 | K5: 0.97996822 | L5: 0.94502119 | M5: 0.92284829 | N5: =AVERAGE(L5:M5) -> 0.93393474 | O5: 1.3375 | P5: 10.576766 | Q5: 10.20831 | R5: 89.423234 | S5: 89.791689
A6: ALGN US Equity | B6: ALIGN TECHNOLOGY INC | C6: ALGN US | D6: 7820.7179 | E6: 98.139999 | F6: 79.6894 | G6: 0 | H6: 419.948 | I6: 68.98 | J6: 206.638 | K6: 1.1346158 | L6: 1.2034391 | M6: 1.0434969 | N6: =AVERAGE(L6:M6) -> 1.123468 | O6: #N/A N/A | P6: 0 | Q6: 0 | R6: 100 | S6: 100
A7: XRAY US Equity | B7: DENTSPLY SIRONA INC | C7: XRAY US | D7: 13409.538 | E7: 58.080002 | F7: 230.8805 | G7: 1586.2 | H7: 330.7 | I7: 229 | J7: 590.10769 | K7: 0.86219967 | L7: 0.95597805 | M7: 0.89573395 | N7: =AVERAGE(L7:M7) -> 0.925856 | O7: 0.29 | P7: 19.488108 | Q7: 16.16242 | R7: 80.511894 | S7: 83.837578
A8: INGN US Equity | B8: INOGEN INC | C8: INGN US | D8: 1315.5269 | E8: 64.93 | F8: 20.26069 | G8: 0.08 | H8: 86.009 | I8: 8.741 | J8: 29.063 | K8: 1.0324547 | M8: 0.95475526 | N8: =AVERAGE(L8:M8) -> 0.95475526 | O8: #N/A N/A | P8: 0 | Q8: 0 | R8: 100 | S8: 100
A9: ATRI US Equity | B9: ATRION CORPORATION | C9: ATRI US | D9: 894.80934 | E9: 490.5 | F9: 1.82428 | G9: 0 | H9: 23.747 | I9: 13.189 | J9: 53.733 | K9: 0.60018222 | L9: 0.78480538 | M9: 0.66128373 | N9: =AVERAGE(L9:M9) -> 0.72304455 | O9: 3.3 | P9: 25.167456 | Q9: 21.060675 | R9: 74.832542 | S9: 78.939323
A10: HYH US Equity | B10: HALYARD HEALTH INC | C10: HYH US | D10: 1781.0868 | E10: 38.16 | F10: 46.67418 | G10: 589.4 | H10: 86.7 | I10: 56.7 | J10: 220.5 | K10: 1.274704 | M10: 1.0748349 | N10: =AVERAGE(L10:M10) -> 1.0748349 | O10: #N/A N/A | P10: 0 | R10: 100
A11: TFX US Equity | B11: TELEFLEX INC | C11: TFX US | D11: 6803.1417 | E11: 154.42999 | F11: 44.05324 | G11: 1031.862 | H11: 499.459 | I11: 121.466 | J11: 434.995 | K11: 0.88072526 | L11: 0.83720429 | M11: 0.84825644 | N11: =AVERAGE(L11:M11) -> 0.84273037 | O11: 1.36 | P11: 22.6213 | Q11: 23.952942 | R11: 77.3787 | S11: 76.047058
A12: HOLX US Equity | B12: HOLOGIC INC | C12: HOLX US | D12: 10850.419 | E12: 39 | F12: 278.2159 | G12: 3345.4 | H12: 548.4 | I12: 272.8 | J12: 1039.3 | K12: 1.021291 | L12: 0.99125447 | M12: 0.97168927 | N12: =AVERAGE(L12:M12) -> 0.98147187 | O12: #N/A N/A | P12: 0 | Q12: 0 | R12: 100 | S12: 100
A13: IART US Equity | B13: INTEGRA LIFESCIENCES HOLDING | C13: IART US | D13: 2896.291 | E13: 77.470001 | F13: 37.38597 | G13: 687.748 | H13: 107.598 | I13: 59.674 | J13: 208.91 | K13: 0.88603733 | L13: 0.90455993 | M13: 0.86697168 | N13: =AVERAGE(L13:M13) -> 0.8857658 | O13: #N/A N/A | P13: 0 | Q13: 0 | R13: 100 | S13: 100
A14: ALOG US Equity | B14: ANALOGIC CORP | C14: ALOG US | D14: 1031.9671 | E14: 82.849998 | F14: 12.45585 | G14: 0 | H14: 141.952 | I14: 11.273 | J14: 77.649 | K14: 0.92122422 | L14: 0.91208654 | M14: 0.8314871 | N14: =AVERAGE(L14:M14) -> 0.87178682 | O14: 0.4 | P14: 49.067562 | Q14: 40.907066 | R14: 50.932438 | S14: 59.092934
A15: CTLT US Equity | B15: CATALENT INC | C15: CTLT US | D15: 2954.0386 | E15: 23.68 | F15: 124.7483 | G15: 1937.3 | H15: 132.1 | I15: 66.5 | J15: 388.3 | K15: 1.2103285 | M15: 1.0239408 | N15: =AVERAGE(L15:M15) -> 1.0239408 | O15: #N/A N/A | P15: 0 | Q15: 0 | R15: 100 | S15: 100
A16: VAR US Equity | B16: VARIAN MEDICAL SYSTEMS INC | C16: VAR US | D16: 8427.4544 | E16: 90.220001 | F16: 93.41005 | G16: 667.1 | H16: 843.5 | I16: 209.829 | J16: 684.8 | K16: 0.95588769 | L16: 0.97084178 | M16: 0.97888113 | N16: =AVERAGE(L16:M16) -> 0.97486145 | O16: #N/A N/A | P16: 0 | Q16: 0 | R16: 100 | S16: 100
B20: (BICS --> Algo Match)
B21: Company | C21: Price | D21: Shares Outstanding | E21: MKT_Equity | F21: Debt | G21: Cash | H21: EV | I21: EBITDA | J21: EBITDA Mult | K21: Beta
B22: ALIGN TECHNOLOGY INC | C22: 90 | D22: =F6*1000000 -> 79689400 | E22: =C22*D22 -> 7.172046e+09 | F22: =G6*1000000 -> 0 | G22: =H6*1000000 -> 419948000 | H22: =E22+F22-G22 -> 6.752098e+09 | I22: =I6*1000000 -> 68980000 | J22: =H22/I22 -> 97.884865 | K22: =N6 -> 1.123468
B23: DENTSPLY SIRONA INC | C23: =E7 -> 58.080002 | D23: =F7*1000000 -> 2.308805e+08 | E23: =C23*D23 -> 1.340954e+10 | F23: =G7*1000000 -> 1586200000 | G23: =H7*1000000 -> 330700000 | H23: =E23+F23-G23 -> 1.466504e+10 | I23: =I7*1000000 -> 229000000 | J23: =H23/I23 -> 64.039475 | K23: =N7 -> 0.925856
B24: INOGEN INC | C24: =E8 -> 64.93 | D24: =F8*1000000 -> 20260690 | E24: =C24*D24 -> 1.3155266e+09 | F24: =G8*1000000 -> 80000 | G24: =H8*1000000 -> 86009000 | H24: =E24+F24-G24 -> 1.2295976e+09 | I24: =I8*1000000 -> 8741000 | J24: =H24/I24 -> 140.67013 | K24: =N8 -> 0.95475526 | S24: Max | T24: =MAX(R41:V45) -> 73.549098
B25: ATRION CORPORATION | C25: =E9 -> 490.5 | D25: =F9*1000000 -> 1824280 | E25: =C25*D25 -> 894809340 | F25: =G9*1000000 -> 0 | G25: =H9*1000000 -> 23747000 | H25: =E25+F25-G25 -> 871062340 | I25: =I9*1000000 -> 13189000 | J25: =H25/I25 -> 66.044608 | K25: =N9 -> 0.72304455 | S25: Min | T25: =MIN(R41:V45) -> 45.368275
B26: HALYARD HEALTH INC | C26: =E10 -> 38.16 | D26: =F10*1000000 -> 46674180 | E26: =C26*D26 -> 1.7810867e+09 | F26: =G10*1000000 -> 589400000 | G26: =H10*1000000 -> 86700000 | H26: =E26+F26-G26 -> 2.2837867e+09 | I26: =I10*1000000 -> 56700000 | J26: =H26/I26 -> 40.278425 | K26: =N10 -> 1.0748349 | S26: Avg | T26: =AVERAGE(R41:V45) -> 58.448398
B27: TELEFLEX INC | C27: =E11 -> 154.42999 | D27: =F11*1000000 -> 44053240 | E27: =C27*D27 -> 6.8031415e+09 | F27: =G11*1000000 -> 1.031862e+09 | G27: =H11*1000000 -> 499459000 | H27: =E27+F27-G27 -> 7.3355445e+09 | I27: =I11*1000000 -> 121466000 | J27: =H27/I27 -> 60.391752 | K27: =N11 -> 0.84273037
B28: HOLOGIC INC | C28: =E12 -> 39 | D28: =F12*1000000 -> 278215900 | E28: =C28*D28 -> 10850420100 | F28: =G12*1000000 -> 3345400000 | G28: =H12*1000000 -> 548400000 | H28: =E28+F28-G28 -> 13647420100 | I28: =I12*1000000 -> 2.728e+08 | J28: =H28/I28 -> 50.0272 | K28: =N12 -> 0.98147187 | Z28: (Mult)
B29: INTEGRA LIFESCIENCES HOLDING | C29: =E13 -> 77.470001 | D29: =F13*1000000 -> 37385970 | E29: =C29*D29 -> 2.8962911e+09 | F29: =G13*1000000 -> 687748000 | G29: =H13*1000000 -> 107598000 | H29: =E29+F29-G29 -> 3.4764411e+09 | I29: =I13*1000000 -> 59674000 | J29: =H29/I29 -> 58.257217 | K29: =N13 -> 0.8857658 | N29: =J43 -> 58.24056 | O29: =P29-2 -> 51.19 | P29: =Q29-2 -> 53.19 | Q29: =R29-2 -> 55.19 | R29: =S29-2 -> 57.19 | S29: =T29-2 -> 59.19 | T29: 61.19 | U29: =T29+2 -> 63.19 | V29: =U29+2 -> 65.19 | W29: =V29+2 -> 67.19 | X29: =W29+2 -> 69.19 | Y29: =X29+2 -> 71.19 | Z29: =Y29+2 -> 73.19
B30: ANALOGIC CORP | C30: =E14 -> 82.849998 | D30: =F14*1000000 -> 12455850 | E30: =C30*D30 -> 1.0319672e+09 | F30: =G14*1000000 -> 0 | G30: =H14*1000000 -> 141952000 | H30: =E30+F30-G30 -> 8.9001515e+08 | I30: =I14*1000000 -> 11273000 | J30: =H30/I30 -> 78.951047 | K30: =N14 -> 0.87178682 | N30: =N31*(1-10%) -> 17533790 | O30: 16.532973 | P30: 16.973027 | Q30: 17.41308 | R30: 17.853133 | S30: 18.293187 | T30: 18.73324 | U30: 19.173293 | V30: 19.613346 | W30: 20.0534 | X30: 20.493453 | Y30: 20.933506 | Z30: 21.373559
B31: CATALENT INC | C31: =E15 -> 23.68 | D31: =F15*1000000 -> 124748300 | E31: =C31*D31 -> 2.9540398e+09 | F31: =G15*1000000 -> 1937300000 | G31: =H15*1000000 -> 132100000 | H31: =E31+F31-G31 -> 4.7592398e+09 | I31: =I15*1000000 -> 66500000 | J31: =H31/I31 -> 71.567516 | K31: =N15 -> 1.0239408 | N31: =N32*(1-10%) -> 19481989 | O31: 17.784436 | P31: 18.273384 | Q31: 18.762332 | R31: 19.25128 | S31: 19.740228 | T31: 20.229176 | U31: 20.718125 | V31: 21.207073 | W31: 21.696021 | X31: 22.184969 | Y31: 22.673917 | Z31: 23.162865
B32: VARIAN MEDICAL SYSTEMS INC | C32: =E16 -> 90.220001 | D32: =F16*1000000 -> 93410050 | E32: =C32*D32 -> 8.4274548e+09 | F32: =G16*1000000 -> 667100000 | G32: =H16*1000000 -> 843500000 | H32: =E32+F32-G32 -> 8.2510548e+09 | I32: =I16*1000000 -> 209829000 | J32: =H32/I32 -> 39.322757 | K32: =N16 -> 0.97486145 | N32: =N33*(1-10%) -> 21646655 | O32: 19.17495 | P32: 19.718226 | Q32: 20.261501 | R32: 20.804777 | S32: 21.348053 | T32: 21.891328 | U32: 22.434604 | V32: 22.97788 | W32: 23.521155 | X32: 24.064431 | Y32: 24.607706 | Z32: 25.150982
N33: =N34*(1-10%) -> 24051839 | O33: 20.719966 | P33: 21.323605 | Q33: 21.927245 | R33: 22.530884 | S33: 23.134524 | T33: 23.738164 | U33: 24.341803 | V33: 24.945443 | W33: 25.549082 | X33: 26.152722 | Y33: 26.756362 | Z33: 27.360001
I34: Average = | J34: =AVERAGE(J23:J32) -> 66.955013 | K34: =AVERAGE(K22:K32) -> 0.94386508 | N34: =N35*(1-10%) -> 26724265 | O34: 22.43665 | P34: 23.10736 | Q34: 23.778071 | R34: 24.448782 | S34: 25.119492 | T34: 25.790203 | U34: 26.460914 | V34: 27.131624 | W34: 27.802335 | X34: 28.473046 | Y34: 29.143756 | Z34: 29.814467
I35: Excl. Outlier = | J35: =(SUM(J23:J32)-MAX(J23:J32)-MIN(J23:J32))/(COUNT(J23:J32)-2) -> 61.194655 | N35: =N36*(1-10%) -> 29693628 | O35: 24.344076 | P35: 25.08931 | Q35: 25.834544 | R35: 26.579778 | S35: 27.325012 | T35: 28.070247 | U35: 28.815481 | V35: 29.560715 | W35: 30.305949 | X35: 31.051183 | Y35: 31.796417 | Z35: 32.541651
N36: =N37*(1-10%) -> 32992920 | O36: 26.463439 | P36: 27.291477 | Q36: 28.119515 | R36: 28.947553 | S36: 29.775591 | T36: 30.603628 | U36: 31.431666 | V36: 32.259704 | W36: 33.087742 | X36: 33.91578 | Y36: 34.743818 | Z36: 35.571856
I37: EBITDA | J37: =I22 -> 68980000 | N37: =N38*(1-10%) -> 36658800 | O37: 28.818287 | P37: 29.738329 | Q37: 30.658371 | R37: 31.578413 | S37: 32.498455 | T37: 33.418497 | U37: 34.338539 | V37: 35.258581 | W37: 36.178623 | X37: 37.098665 | Y37: 38.018707 | Z37: 38.93875
I38: EV = | J38: =J37*J35 -> 4.2212073e+09 | N38: =N39*(1-10%) -> 40732000 | O38: 31.434784 | P38: 32.457053 | Q38: 33.479322 | R38: 34.501591 | S38: 35.52386 | T38: 36.546129 | U38: 37.568398 | V38: 38.590667 | W38: 39.612936 | X38: 40.635205 | Y38: 41.657474 | Z38: 42.679743
I39: Debt | J39: =F22 -> 0 | N39: =N40*(1-10%) -> 45257778 | O39: 34.342004 | P39: 35.477858 | Q39: 36.613712 | R39: 37.749567 | S39: 38.885421 | T39: 40.021276 | U39: 41.15713 | V39: 42.292984 | W39: 43.428839 | X39: 44.564693 | Y39: 45.700548 | Z39: 46.836402
I40: Cash | J40: =G22 -> 419948000 | N40: =N41*(1-10%) -> 50286420 | O40: 37.572247 | P40: 38.834308 | Q40: 40.096368 | R40: 41.358429 | S40: 42.620489 | T40: 43.882549 | U40: 45.14461 | V40: 46.40667 | W40: 47.668731 | X40: 48.930791 | Y40: 50.192852 | Z40: 51.454912
I41: Equity Value = | J41: =J38-J39+J40 -> 4.6411553e+09 | N41: =N42*(1-10%) -> 55873800 | O41: 41.161407 | P41: 42.563696 | Q41: 43.965986 | R41: 45.368275 | S41: 46.770564 | T41: 48.172854 | U41: 49.575143 | V41: 50.977433 | W41: 52.379722 | X41: 53.782011 | Y41: 55.184301 | Z41: 56.58659
I42: SO: | J42: =D22 -> 79689400 | N42: =N43*(1-10%) -> 62082000 | O42: 45.149362 | P42: 46.707461 | Q42: 48.265561 | R42: 49.82366 | S42: 51.381759 | T42: 52.939859 | U42: 54.497958 | V42: 56.056057 | W42: 57.614157 | X42: 59.172256 | Y42: 60.730355 | Z42: 62.288455
I43: VALUATION: | J43: =J41/J42 -> 58.24056 | N43: 68980000 | O43: 49.580423 | P43: 51.311645 | Q43: 53.042866 | R43: 54.774088 | S43: 56.505309 | T43: 58.236531 | U43: 59.967752 | V43: 61.698974 | W43: 63.430195 | X43: 65.161417 | Y43: 66.892638 | Z43: 68.62386
N44: =N43*(1+10%) -> 75878000 | O44: 54.011485 | P44: 55.915828 | Q44: 57.820172 | R44: 59.724516 | S44: 61.628859 | T44: 63.533203 | U44: 65.437547 | V44: 67.34189 | W44: 69.246234 | X44: 71.150577 | Y44: 73.054921 | Z44: 74.959265
N45: =N44*(1+10%) -> 83465800 | O45: 58.885652 | P45: 60.98043 | Q45: 63.075208 | R45: 65.169986 | S45: 67.264764 | T45: 69.359542 | U45: 71.45432 | V45: 73.549098 | W45: 75.643876 | X45: 77.738654 | Y45: 79.833432 | Z45: 81.92821
N46: =N45*(1+10%) -> 91812380 | O46: 64.247237 | P46: 66.551492 | Q46: 68.855748 | R46: 71.160004 | S46: 73.46426 | T46: 75.768515 | U46: 78.072771 | V46: 80.377027 | W46: 82.681283 | X46: 84.985539 | Y46: 87.289794 | Z46: 89.59405
N47: =N46*(1+10%) -> 1.0099362e+08 | O47: 70.144979 | P47: 72.679661 | Q47: 75.214342 | R47: 77.749023 | S47: 80.283705 | T47: 82.818386 | U47: 85.353067 | V47: 87.887749 | W47: 90.42243 | X47: 92.957111 | Y47: 95.491793 | Z47: 98.026474
N48: =N47*(1+10%) -> 1.1109298e+08 | O48: 76.632496 | P48: 79.420646 | Q48: 82.208795 | R48: 84.996945 | S48: 87.785094 | T48: 90.573244 | U48: 93.361393 | V48: 96.149543 | W48: 98.937692 | X48: 101.72584 | Y48: 104.51399 | Z48: 107.30214
N49: =N48*(1+10%) -> 1.2220228e+08 | O49: 83.768765 | P49: 86.835729 | Q49: 89.902694 | R49: 92.969658 | S49: 96.036622 | T49: 99.103587 | U49: 102.17055 | V49: 105.23752 | W49: 108.30448 | X49: 111.37144 | Y49: 114.43841 | Z49: 117.50537
N50: =N49*(1+10%) -> 1.3442251e+08 | O50: 91.61866 | P50: 94.992321 | Q50: 98.365982 | R50: 101.73964 | S50: 105.1133 | T50: 108.48696 | U50: 111.86063 | V50: 115.23429 | W50: 118.60795 | X50: 121.98161 | Y50: 125.35527 | Z50: 128.72893
N51: =N50*(1+10%) -> 1.4786476e+08 | O51: 100.25355 | P51: 103.96457 | Q51: 107.6756 | R51: 111.38663 | S51: 115.09765 | T51: 118.80868 | U51: 122.51971 | V51: 126.23073 | W51: 129.94176 | X51: 133.65279 | Y51: 137.36381 | Z51: 141.07484
N52: =N51*(1+10%) -> 1.6265123e+08 | O52: 109.75192 | P52: 113.83405 | Q52: 117.91618 | R52: 121.99831 | S52: 126.08044 | T52: 130.16257 | U52: 134.2447 | V52: 138.32683 | W52: 142.40896 | X52: 146.49109 | Y52: 150.57322 | Z52: 154.65535
N53: =N52*(1+10%) -> 1.7891635e+08 | O53: 120.20013 | P53: 124.69047 | Q53: 129.18081 | R53: 133.67116 | S53: 138.1615 | T53: 142.65184 | U53: 147.14219 | V53: 151.63253 | W53: 156.12287 | X53: 160.61321 | Y53: 165.10356 | Z53: 169.5939
N54: =N53*(1+10%) -> 1.9680799e+08 | O54: 131.69316 | P54: 136.63254 | Q54: 141.57192 | R54: 146.51129 | S54: 151.45067 | T54: 156.39005 | U54: 161.32942 | V54: 166.2688 | W54: 171.20818 | X54: 176.14755 | Y54: 181.08693 | Z54: 186.02631
N55: =N54*(1+10%) -> 2.1648879e+08 | O55: 144.3355 | P55: 149.76881 | Q55: 155.20213 | R55: 160.63544 | S55: 166.06876 | T55: 171.50207 | U55: 176.93538 | V55: 182.3687 | W55: 187.80201 | X55: 193.23533 | Y55: 198.66864 | Z55: 204.10196
... N58: =N57*(1+10%) -> 2.8814658e+08 | O58: 190.36624 | P58: 197.59798 | Q58: 204.82972 | R58: 212.06146 | S58: 219.29321 | T58: 226.52495 | U58: 233.75669 | V58: 240.98843 | W58: 248.22017 | X58: 255.45191 | Y58: 262.68366 | Z58: 269.9154
M59: EBITDA_LQ | N59: =N58*(1+10%) -> 3.1696124e+08 | O59: 208.87588 | P59: 216.8308 | Q59: 224.78571 | R59: 232.74063 | S59: 240.69555 | T59: 248.65046 | U59: 256.60538 | V59: 264.56029 | W59: 272.51521 | X59: 280.47012 | Y59: 288.42504 | Z59: 296.37996

Sheet div
A2: DENTSPLY SIRONA Inc (XRAY US) - div
A3: Dental
A4: In Millions of USD except Per Share | C4: FY 2007 | D4: FY 2008 | E4: FY 2009 | F4: FY 2010 | G4: FY 2011 | H4: FY 2012 | I4: FY 2013 | J4: FY 2014 | K4: FY 2015 | L4: Last 12M | M4: FY 2016 Est | N4: FY 2017 Est
A5: 12 Months Ending | C5: 12/31/2007 | D5: 12/31/2008 | E5: 12/31/2009 | F5: 12/31/2010 | G5: 12/31/2011 | H5: 12/31/2012 | I5: 12/31/2013 | J5: 12/31/2014 | K5: 12/31/2015 | L5: 09/30/2016 | M5: 12/31/2016 | N5: 12/31/2017
A6: Dividends per Share | B6: EQY_DPS | C6: 0.165 | D6: 0.185 | E6: 0.2 | F6: 0.2 | G6: 0.205 | H6: 0.22 | I6: 0.25 | J6: 0.265 | K6: 0.29 | L6: 0.305 | M6: 0.295 | N6: 0.328
A7: BEst Div Yld | B7: BEST_DIV_YLD | C7: 0.366504 | D7: 0.637394 | E7: 0.568666 | F7: 0.614574 | G7: 0.614461 | H7: 0.537743 | I7: 0.49505 | J7: 0.497466 | K7: 0.468365 | L7: 0.53719008 | M7: 0.50792011 | N7: 0.56473829
A8: Dividend Payout Ratio | B8: DVD_PAYOUT_RATIO | C8: 9.640136 | D8: 9.693908 | E8: 10.799685 | F8: 10.787782 | G8: 11.849337 | H8: 9.931798 | I8: 11.387823 | J8: 11.646131 | K8: 16.16242 | L8: 19.488108 | M8: 10.645976 | N8: 10.814375
A9: Retention Ratio | B9: RETENTION_RATIO | C9: 90.359864 | D9: 90.306092 | E9: 89.200315 | F9: 89.212218 | G9: 88.150663 | H9: 90.068202 | I9: 88.612177 | J9: 88.353869 | K9: 83.83758 | L9: 80.511892
A10: Return on Common Equity | B10: RETURN_COM_EQY | C10: 18.613584 | D10: 18.291542 | E10: 16.039291 | F10: 14.47412 | G10: 13.262235 | H10: 15.490778 | I10: 13.204403 | J10: 13.29615 | K10: 10.782736 | L10: 7.1817172 | M10: 9.928 | N10: 7.738
A11: Return on Assets | B11: RETURN_ON_ASSET | C11: 10.692128 | D11: 10.311318 | E11: 9.268084 | F11: 8.374185 | G11: 6.102817 | H11: 6.460174 | I11: 6.232463 | J11: 6.63998 | K11: 5.551749 | L11: 4.6653541 | M11: 7.55 | N11: 5.99
A12: Source: Bloomberg
A15: Danaher Corp (DHR US) - div
A16: Widely diverse but includes dental
A17: In Millions of USD except Per Share | C17: FY 2007 | D17: FY 2008 | E17: FY 2009 | F17: FY 2010 | G17: FY 2011 | H17: FY 2012 | I17: FY 2013 | J17: FY 2014 | K17: FY 2015 | L17: Last 12M | M17: FY 2016 Est | N17: FY 2017 Est
A18: 12 Months Ending | C18: 12/31/2007 | D18: 12/31/2008 | E18: 12/31/2009 | F18: 12/31/2010 | G18: 12/31/2011 | H18: 12/31/2012 | I18: 12/31/2013 | J18: 12/31/2014 | K18: 12/31/2015 | L18: 09/30/2016 | M18: 12/31/2016 | N18: 12/31/2017
A19: Dividends per Share | B19: EQY_DPS | C19: 0.055 | D19: 0.06 | E19: 0.06 | F19: 0.08 | G19: 0.09 | H19: 0.1 | I19: 0.1 | J19: 0.4 | K19: 0.54 | L19: 0.58 | M19: 0.582 | N19: 0.566
A20: BEst Div Yld | B20: BEST_DIV_YLD | C20: 0.1594 | D20: 0.270361 | E20: 0.203526 | F20: 0.237756 | G20: 0.255242 | H20: 0.231309 | I20: 0.169199 | J20: 0.615754 | K20: 0.767097 | L20: 0.68857997 | M20: 0.75613876 | N20: 0.73535144
A21: Dividend Payout Ratio | B21: DVD_PAYOUT_RATIO | C21: 2.823316 | D21: 2.90362 | E21: 3.620722 | F21: 3.041324 | G21: 3.144506 | H21: 3.0157 | I21: 2.58256 | J21: 11.03771 | K21: 14.484165 | L21: 21.491555 | M21: 16.193656 | N21: 14.405701
A22: Retention Ratio | B22: RETENTION_RATIO | C22: 97.176684 | D22: 97.09638 | E22: 96.379278 | F22: 96.958676 | G22: 96.855494 | H22: 96.9843 | I22: 97.41744 | J22: 88.96229 | K22: 85.515835 | L22: 78.508445
A23: Return on Common Equity | B23: RETURN_COM_EQY | C23: 17.417339 | D23: 13.947428 | E23: 10.74414 | F23: 14.150877 | G23: 14.19048 | H23: 13.319123 | I23: 13.018758 | J23: 11.3558 | K23: 14.266047 | L23: 10.775673 | M23: 11.08 | N23: 11.4
A24: Return on Assets | B24: RETURN_ON_ASSET | C24: 9.031514 | D24: 7.53749 | E24: 6.211066 | F24: 8.576372 | G24: 8.328183 | H24: 7.607515 | I24: 7.971816 | J24: 7.251629 | K24: 7.879935 | L24: 5.4838504 | M24: 5.66 | N24: 5.97
A25: Source: Bloomberg
M27: CAGR | N27: AVG
C28: DHR | D28: 0.055 | E28: 0.06 | F28: 0.06 | G28: 0.08 | H28: 0.09 | I28: 0.1 | J28: 0.1 | K28: 0.4 | L28: 0.54 | P28: Weight
I29: =(I28-H28)/H28 -> 0.11111111 | J29: =(J28-I28)/I28 -> 0 | K29: =(K28-J28)/J28 -> 3 | L29: =(L28-K28)/K28 -> 0.35 | M29: =(L28/H28)^(1/5)-1 -> 0.43096908 | N29: =AVERAGE(I29:L29) -> 0.86527778 | P29: 0.7 | Q29: =M29*P29 -> 0.30167836
C30: XRAY | D30: 0.165 | E30: 0.185 | F30: 0.2 | G30: 0.2 | H30: 0.205 | I30: 0.22 | J30: 0.25 | K30: 0.265 | L30: 0.29 | P30: 0.3 | Q30: =M31*P30 -> 0.021551161
I31: =(I30-H30)/H30 -> 0.073170732 | J31: =(J30-I30)/I30 -> 0.13636364 | K31: =(K30-J30)/J30 -> 0.06 | L31: =(L30-K30)/K30 -> 0.094339623 | M31: =(L30/H30)^(1/5)-1 -> 0.071837204 | N31: =AVERAGE(I31:L31) -> 0.090968498 | Q31: =SUM(Q29:Q30) -> 0.32322952
R33: 2017 | S33: 2018 | T33: 2019 | U33: 2020 | V33: 2021
R34: 0.25 | S34: =R34*(1+$Q$31) -> 0.33080738 | T34: =S34*(1+$Q$31) -> 0.43773409 | U34: =T34*(1+$Q$31) -> 0.57922267 | V34: =U34*(1+$Q$31) -> 0.76644453
Q36: D(0) | R36: =R34 -> 0.25
G37: <NULL> | Q37: CAGR_5_calc | R37: =Q31 -> 0.32322952
Q38: g (adjusted) | R38: 0.01
Q39: WACC | R39: =DCF!B23 -> 0.1048
Q40: D(1) = D(0) x (1 + g) | R40: =R36*(1+R38) -> 0.2525
Q41: Val = D(1)/(r - g) | R41: =R40/(R39-R38) -> 2.6635021
G43: No dividends --> speculation experiment --> not used for Valuation_Final
